Workbook
Name UPDATE: 'Data Sheet'!$E$1

Sheet Data Sheet
A1: COMPANY NAME | B1: ESCORTS KUBOTA LTD | E1: =IF(B2<>B3, "A NEW VERSION OF THE WORKSHEET IS AVAILABLE", "")
A2: LATEST VERSION | B2: 2.1 | E2: PLEASE DO NOT MAKE ANY CHANGES TO THIS SHEET
A3: CURRENT VERSION | B3: 2.1
A5: META
A6: Number of shares | B6: =IF(B9>0, B9/B8, 0) -> 11.18778
A7: Face Value | B7: 10
A8: Current Price | B8: 3306
A9: Market Capitalization | B9: 36986.8
C12: =B18+B20+B21+B22-B19 -> 2932.37
A15: PROFIT & LOSS
A16: Report Date | B16: 42460 | C16: 42825 | D16: 43190 | E16: 43555 | F16: 43921 | G16: 44286 | H16: 44651 | I16: 45016 | J16: 45382 | K16: 45747
A17: Sales | B17: 3431.99 | C17: 4145.33 | D17: 5059.34 | E17: 6262.02 | F17: 5810.09 | G17: 7014.42 | H17: 7282.65 | I17: 8428.69 | J17: 9803.59 | K17: 10243.88
A18: Raw Material Cost | B18: 2409.31 | C18: 2877.78 | D18: 3426.78 | E18: 4481.47 | F18: 3846.68 | G18: 4514.72 | H18: 5045.45 | I18: 6286.53 | J18: 7147.97 | K18: 7066.61
A19: Change in Inventory | B19: 24.88 | C19: 46.49 | D19: 19.36 | E19: 204.54 | F19: 5.58 | G19: -129.92 | H19: 66.94 | I19: 163.65 | J19: 185.97 | K19: -188.53
A20: Power and Fuel | B20: 36.01 | C20: 38.84 | D20: 38.2 | E20: 45.44 | F20: 40.07 | G20: 38.37 | H20: 40.59 | I20: 45.84 | J20: 50.59 | K20: 46.37
A21: Other Mfr. Exp | B21: 98.37 | C21: 137.75 | D21: 167.41 | E21: 215.43 | F21: 205.6 | G21: 204.74 | H21: 232.41 | I21: 289.65 | J21: 348.14 | K21: 385.06
A22: Employee Cost | B22: 413.56 | C22: 422.1 | D22: 460.47 | E22: 492.76 | F22: 526.59 | G22: 555.41 | H22: 549.41 | I22: 613.83 | J22: 706.01 | K22: 781.22
A23: Selling and admin | B23: 305 | C23: 344.98 | D23: 362 | E23: 431.46 | F23: 423.61 | G23: 370.27 | H23: 394.61 | I23: 491.31 | J23: 472.55 | K23: 488.89
A24: Other Expenses | B24: 33.67 | C24: 102.59 | D24: 70.49 | E24: 77.43 | F24: 111.8 | G24: 74.97 | H24: 121.06 | I24: 95.14 | J24: 133.93 | K24: 123.01
A25: Other Income | B25: 30.66 | C25: 35.85 | D25: 58.44 | E25: 99.19 | F25: 88.38 | G25: 160.38 | H25: 173.8 | I25: 227.88 | J25: 525.37 | K25: 600.53
A26: Depreciation | B26: 58.13 | C26: 63.42 | D26: 73.22 | E26: 87.21 | F26: 107.22 | G26: 118.28 | H26: 132.06 | I26: 150.06 | J26: 224.06 | K26: 243.65
A27: Interest | B27: 51.06 | C27: 32.21 | D27: 29.49 | E27: 19.54 | F27: 17.23 | G27: 13.34 | H27: 14.97 | I27: 13.27 | J27: 41.66 | K27: 29.17
... A31: Dividend Amount | B31: 14.71 | C31: 18.39 | D31: 24.52 | E31: 30.64 | F31: 30.64 | G31: 101.12 | H31: 92.36 | I31: 92.36 | J31: 198.9 | K31: 313.26
A40: Quarters
A41: Report Date | B41: 44926 | C41: 45016 | D41: 45107 | E41: 45199 | F41: 45291 | G41: 45382 | H41: 45473 | I41: 45565 | J41: 45657 | K41: 45747
A42: Sales | B42: 2291.35 | C42: 2214.48 | D42: 2355.17 | E42: 2477.71 | F42: 2727.61 | G42: 2300.66 | H42: 2818.39 | I42: 2277.25 | J42: 2948.02 | K42: 2444.88
A43: Expenses | B43: 2105.96 | C43: 1981.32 | D43: 2024.12 | E43: 2213.52 | F43: 2402.32 | G43: 2015.25 | H43: 2450.99 | I43: 2047.43 | J43: 2615.74 | K43: 2157.63
A44: Other Income | B44: 91.68 | C44: 86.46 | D44: 99.02 | E44: 93.75 | F44: 128.6 | G44: 132.77 | H44: 103.04 | I44: 140.05 | J44: 142.6 | K44: 177.6
A45: Depreciation | B45: 37.97 | C45: 38.37 | D45: 40.3 | E45: 58.34 | F45: 56.62 | G45: 59.24 | H45: 61.63 | I45: 61.07 | J45: 61.53 | K45: 61.97
A46: Interest | B46: 3.48 | C46: 3.63 | D46: 3.43 | E46: 9.43 | F46: 11.16 | G46: 11.66 | H46: 10.73 | I46: 9.79 | J46: 3.54 | K46: 5.14
A47: Profit before tax | B47: 235.62 | C47: 277.62 | D47: 386.34 | E47: 290.17 | F47: 386.11 | G47: 347.28 | H47: 398.08 | I47: 299.01 | J47: 409.81 | K47: 397.74
A48: Tax | B48: 54.82 | C48: 61.16 | D48: 96.45 | E48: 79.66 | F48: 87.59 | G48: 77.3 | H48: 96.4 | I48: -25.21 | J48: 89.18 | K48: 79.32
A49: Net profit | B49: 180.82 | C49: 216.49 | D49: 289.9 | E49: 210.53 | F49: 298.51 | G49: 269.99 | H49: 301.65 | I49: 324.23 | J49: 320.64 | K49: 318.42
A50: Operating Profit | B50: 185.39 | C50: 233.16 | D50: 331.05 | E50: 264.19 | F50: 325.29 | G50: 285.41 | H50: 367.4 | I50: 229.82 | J50: 332.28 | K50: 287.25
A55: BALANCE SHEET
A56: Report Date | B56: 42460 | C56: 42825 | D56: 43190 | E56: 43555 | F56: 43921 | G56: 44286 | H56: 44651 | I56: 45016 | J56: 45382 | K56: 45747
A57: Equity Share Capital | B57: 122.58 | C57: 122.58 | D57: 122.58 | E57: 122.58 | F57: 122.58 | G57: 134.83 | H57: 131.94 | I57: 131.94 | J57: 110.5 | K57: 111.88
A58: Reserves | B58: 1343.9 | C58: 1498.35 | D58: 2092.56 | E58: 2550.91 | F58: 2994.82 | G58: 4891.3 | H58: 7467.96 | I58: 8054.77 | J58: 9278.01 | K58: 10254.92
A59: Borrowings | B59: 368.12 | C59: 265.43 | D59: 51.09 | E59: 280.96 | F59: 47.67 | G59: 60.61 | H59: 51.95 | I59: 57.3 | J59: 448.46 | K59: 105.18
A60: Other Liabilities | B60: 1133.58 | C60: 1312.86 | D60: 1706.3 | E60: 1752.52 | F60: 1848.89 | G60: 1791.43 | H60: 1455.89 | I60: 1840.81 | J60: 2563.39 | K60: 2622.71
A61: Total | B61: 2968.18 | C61: 3199.22 | D61: 3972.53 | E61: 4706.97 | F61: 5013.96 | G61: 6878.17 | H61: 9107.74 | I61: 10084.82 | J61: 12400.36 | K61: 13094.69
A62: Net Block | B62: 1539.02 | C62: 1581.14 | D62: 1587.8 | E62: 1647.23 | F62: 1702.41 | G62: 1796.23 | H62: 1841.05 | I62: 1891.15 | J62: 2165.28 | K62: 2053.18
A63: Capital Work in Progress | B63: 58.43 | C63: 34.7 | D63: 65.72 | E63: 79.96 | F63: 124.66 | G63: 64.69 | H63: 87.8 | I63: 113.68 | J63: 161.4 | K63: 152.54
A64: Investments | B64: 63.66 | C64: 212.34 | D64: 549.04 | E64: 490.79 | F64: 797.36 | G64: 1938.02 | H64: 4835.84 | I64: 4766.69 | J64: 5019.48 | K64: 5605.21
A65: Other Assets | B65: 1307.07 | C65: 1371.04 | D65: 1769.97 | E65: 2488.99 | F65: 2389.53 | G65: 3079.23 | H65: 2343.05 | I65: 3313.3 | J65: 5054.2 | K65: 5283.76
A66: Total | B66: 2968.18 | C66: 3199.22 | D66: 3972.53 | E66: 4706.97 | F66: 5013.96 | G66: 6878.17 | H66: 9107.74 | I66: 10084.82 | J66: 12400.36 | K66: 13094.69
A67: Receivables | B67: 374.97 | C67: 456.45 | D67: 592 | E67: 931.05 | F67: 731.86 | G67: 657.58 | H67: 792.62 | I67: 1179.65 | J67: 1427.91 | K67: 1331.84
... A70: No. of Equity Shares | B70: 122576878 | C70: 122576878 | D70: 122576878 | E70: 122576878 | F70: 122576878 | G70: 134834566 | H70: 131940604 | I70: 131940604 | J70: 110498261 | K70: 111877754
A71: New Bonus Shares
A72: Face value | B72: 10 | C72: 10 | D72: 10 | E72: 10 | F72: 10 | G72: 10 | H72: 10 | I72: 10 | J72: 10 | K72: 10
A80: CASH FLOW:
A81: Report Date | B81: 42460 | C81: 42825 | D81: 43190 | E81: 43555 | F81: 43921 | G81: 44286 | H81: 44651 | I81: 45016 | J81: 45382 | K81: 45747
A82: Cash from Operating Activity | B82: 212.24 | C82: 303.83 | D82: 460.08 | E82: -234.31 | F82: 797.16 | G82: 1128.66 | H82: 32.28 | I82: 223.91 | J82: 788.6 | K82: 1003.19
A83: Cash from Investing Activity | B83: -44.09 | C83: -154.61 | D83: -374.18 | E83: -17.66 | F83: -420.87 | G83: -2195.15 | H83: -1856.39 | I83: -62.05 | J83: -759.06 | K83: -193.85
A84: Cash from Financing Activity | B84: -190.89 | C84: -113.12 | D84: -0.99 | E84: 190.89 | F84: -300.45 | G84: 1003.34 | H84: 1809.88 | I84: -71.22 | J84: 24.77 | K84: -701.86
A85: Net Cash Flow | B85: -22.74 | C85: 36.1 | D85: 84.91 | E85: -61.08 | F85: 75.84 | G85: -63.15 | H85: -14.23 | I85: 90.64 | J85: 54.31 | K85: 107.48
A90: PRICE: | B90: 139.25 | C90: 538.75 | D90: 818.1 | E90: 796.05 | F90: 662.6 | G90: 1287.8 | H90: 1690.85 | I90: 1891.05 | J90: 2777.3 | K90: 3250.05
A92: DERIVED:
A93: Adjusted Equity Shares in Cr | B93: 12.26 | C93: 12.26 | D93: 12.26 | E93: 12.26 | F93: 12.26 | G93: 13.48 | H93: 13.19 | I93: 13.19 | J93: 11.05 | K93: 11.19

Sheet HISTORICAL FS
B2: ="HISTORICAL FINANCIAL STATEMENT - "&'Data Sheet'!B1 -> HISTORICAL FINANCIAL STATEMENT - ESCORTS KUBOTA LTD
B3: YEARS | C3: ='Data Sheet'!B16 -> 42460 | D3: ='Data Sheet'!C16 -> 42825 | E3: ='Data Sheet'!D16 -> 43190 | F3: ='Data Sheet'!E16 -> 43555 | G3: ='Data Sheet'!F16 -> 43921 | H3: ='Data Sheet'!G16 -> 44286 | I3: ='Data Sheet'!H16 -> 44651 | J3: ='Data Sheet'!I16 -> 45016 | ... L3: ='Data Sheet'!K16 -> 45747 | M3: LTM
A4: # | B4: INCOME STATEMENT
B5: Sales growth | C5: =IFERROR('Data Sheet'!B17,0) -> 3431.99 | D5: =IFERROR('Data Sheet'!C17,0) -> 4145.33 | E5: =IFERROR('Data Sheet'!D17,0) -> 5059.34 | F5: =IFERROR('Data Sheet'!E17,0) -> 6262.02 | G5: =IFERROR('Data Sheet'!F17,0) -> 5810.09 | H5: =IFERROR('Data Sheet'!G17,0) -> 7014.42 | I5: =IFERROR('Data Sheet'!H17,0) -> 7282.65 | J5: =IFERROR('Data Sheet'!I17,0) -> 8428.69 | ... L5: =IFERROR('Data Sheet'!K17,0) -> 10243.88 | M5: =IFERROR(SUM('Data Sheet'!H42:K42),0) -> 10488.54
B6: Sales growth | C6: - | D6: =D5/C5-1 -> 0.20785026 | E6: =E5/D5-1 -> 0.22049149 | F6: =F5/E5-1 -> 0.2377148 | G6: =G5/F5-1 -> -0.072170003 | H6: =H5/G5-1 -> 0.2072825 | I6: =I5/H5-1 -> 0.038239797 | J6: =J5/I5-1 -> 0.15736579 | K6: =K5/J5-1 -> 0.16312143 | ... M6: =M5/L5-1 -> 0.023883529
B8: COGS | C8: =IFERROR(SUM('Data Sheet'!B18,'Data Sheet'!B20,'Data Sheet'!B21,'Data Sheet'!B22)-1*'Data Sheet'!B19,0) -> 2932.37 | D8: =IFERROR(SUM('Data Sheet'!C18,'Data Sheet'!C20,'Data Sheet'!C21,'Data Sheet'!C22)-1*'Data Sheet'!C19,0) -> 3429.98 | E8: =IFERROR(SUM('Data Sheet'!D18,'Data Sheet'!D20,'Data Sheet'!D21,'Data Sheet'!D22)-1*'Data Sheet'!D19,0) -> 4073.5 | F8: =IFERROR(SUM('Data Sheet'!E18,'Data Sheet'!E20,'Data Sheet'!E21,'Data Sheet'!E22)-1*'Data Sheet'!E19,0) -> 5030.56 | G8: =IFERROR(SUM('Data Sheet'!F18,'Data Sheet'!F20,'Data Sheet'!F21,'Data Sheet'!F22)-1*'Data Sheet'!F19,0) -> 4613.36 | H8: =IFERROR(SUM('Data Sheet'!G18,'Data Sheet'!G20,'Data Sheet'!G21,'Data Sheet'!G22)-1*'Data Sheet'!G19,0) -> 5443.16 | I8: =IFERROR(SUM('Data Sheet'!H18,'Data Sheet'!H20,'Data Sheet'!H21,'Data Sheet'!H22)-1*'Data Sheet'!H19,0) -> 5800.92 | J8: =IFERROR(SUM('Data Sheet'!I18,'Data Sheet'!I20,'Data Sheet'!I21,'Data Sheet'!I22)-1*'Data Sheet'!I19,0) -> 7072.2 | ... L8: =IFERROR(SUM('Data Sheet'!K18,'Data Sheet'!K20,'Data Sheet'!K21,'Data Sheet'!K22)-1*'Data Sheet'!K19,0) -> 8467.79 | M8: =IFERROR(SUM('Data Sheet'!H43:K43),0) -> 9271.79
B9: COGS % of sales | C9: =C8/C5 -> 0.85442265 | D9: =D8/D5 -> 0.82743232 | E9: =E8/E5 -> 0.80514454 | F9: =F8/F5 -> 0.80334461 | G9: =G8/G5 -> 0.79402557 | H9: =H8/H5 -> 0.77599573 | I9: =I8/I5 -> 0.79653972 | J9: =J8/J5 -> 0.83906277 | ... L9: =L8/L5 -> 0.82661941 | M9: -
B11: GROSS PROFIT | C11: =C5-C8 -> 499.62 | D11: =D5-D8 -> 715.35 | E11: =E5-E8 -> 985.84 | F11: =F5-F8 -> 1231.46 | G11: =G5-G8 -> 1196.73 | H11: =H5-H8 -> 1571.26 | I11: =I5-I8 -> 1481.73 | J11: =J5-J8 -> 1356.49 | ... M11: =M5-M8 -> 1216.75
B12: Gross margin | C12: =C11/C5 -> 0.14557735 | D12: =D11/D5 -> 0.17256768 | E12: =E11/E5 -> 0.19485546 | F12: =F11/F5 -> 0.19665539 | G12: =G11/G5 -> 0.20597443 | H12: =H11/H5 -> 0.22400427 | I12: =I11/I5 -> 0.20346028 | J12: =J11/J5 -> 0.16093723 | ... M12: =M11/M5 -> 0.11600757
B14: SELLING AND GENERAL EXPENSES | C14: =IFERROR(SUM('Data Sheet'!B23,'Data Sheet'!B24),0) -> 338.67 | D14: =IFERROR(SUM('Data Sheet'!C23,'Data Sheet'!C24),0) -> 447.57 | E14: =IFERROR(SUM('Data Sheet'!D23,'Data Sheet'!D24),0) -> 432.49 | F14: =IFERROR(SUM('Data Sheet'!E23,'Data Sheet'!E24),0) -> 508.89 | G14: =IFERROR(SUM('Data Sheet'!F23,'Data Sheet'!F24),0) -> 535.41 | H14: =IFERROR(SUM('Data Sheet'!G23,'Data Sheet'!G24),0) -> 445.24 | I14: =IFERROR(SUM('Data Sheet'!H23,'Data Sheet'!H24),0) -> 515.67 | J14: =IFERROR(SUM('Data Sheet'!I23,'Data Sheet'!I24),0) -> 586.45 | ... L14: =IFERROR(SUM('Data Sheet'!K23,'Data Sheet'!K24),0) -> 611.9
B15: S&G EX % of sales | C15: =C14/C5 -> 0.098680357 | D15: =D14/D5 -> 0.10796969 | E15: =E14/E5 -> 0.085483482 | F15: =F14/F5 -> 0.081266109 | G15: =G14/G5 -> 0.092151757 | H15: =H14/H5 -> 0.063474956 | I15: =I14/I5 -> 0.070808016 | J15: =J14/J5 -> 0.069577835 | ... M15: =M14/M5 -> 0
B17: EBITDA | C17: =C11-C14 -> 160.95 | D17: =D11-D14 -> 267.78 | E17: =E11-E14 -> 553.35 | F17: =F11-F14 -> 722.57 | G17: =G11-G14 -> 661.32 | H17: =H11-H14 -> 1126.02 | I17: =I11-I14 -> 966.06 | J17: =J11-J14 -> 770.04 | ... M17: =M11-M14 -> 1216.75
B18: EBITDA margins | C18: =C17/C5 -> 0.04689699 | D18: =D17/D5 -> 0.064597993 | E18: =E17/E5 -> 0.10937197 | F18: =F17/F5 -> 0.11538928 | G18: =G17/G5 -> 0.11382268 | H18: =H17/H5 -> 0.16052931 | I18: =I17/I5 -> 0.13265226 | J18: =J17/J5 -> 0.091359393 | ... M18: =M17/M5 -> 0.11600757
B20: INTEREST | C20: =IFERROR('Data Sheet'!B27,0) -> 51.06 | D20: =IFERROR('Data Sheet'!C27,0) -> 32.21 | E20: =IFERROR('Data Sheet'!D27,0) -> 29.49 | F20: =IFERROR('Data Sheet'!E27,0) -> 19.54 | G20: =IFERROR('Data Sheet'!F27,0) -> 17.23 | H20: =IFERROR('Data Sheet'!G27,0) -> 13.34 | I20: =IFERROR('Data Sheet'!H27,0) -> 14.97 | J20: =IFERROR('Data Sheet'!I27,0) -> 13.27 | ... L20: =IFERROR('Data Sheet'!K27,0) -> 29.17 | M20: =IFERROR(SUM('Data Sheet'!H46:K46),0) -> 29.2
B21: interest % of sales | C21: =C20/C5 -> 0.014877666 | D21: =D20/D5 -> 0.0077701896 | E21: =E20/E5 -> 0.0058288235 | F21: =F20/F5 -> 0.0031203988 | G21: =G20/G5 -> 0.0029655307 | H21: =H20/H5 -> 0.0019017966 | I21: =I20/I5 -> 0.0020555704 | J21: =J20/J5 -> 0.0015743846 | ... M21: =M20/M5 -> 0.0027839909
B23: DEPRICIATION | C23: =IFERROR('Data Sheet'!B26,0) -> 58.13 | D23: =IFERROR('Data Sheet'!C26,0) -> 63.42 | E23: =IFERROR('Data Sheet'!D26,0) -> 73.22 | F23: =IFERROR('Data Sheet'!E26,0) -> 87.21 | G23: =IFERROR('Data Sheet'!F26,0) -> 107.22 | H23: =IFERROR('Data Sheet'!G26,0) -> 118.28 | I23: =IFERROR('Data Sheet'!H26,0) -> 132.06 | J23: =IFERROR('Data Sheet'!I26,0) -> 150.06 | ... L23: =IFERROR('Data Sheet'!K26,0) -> 243.65 | M23: =IFERROR(SUM('Data Sheet'!H45:K45),0) -> 246.2
B24: Depriciation % of sales | C24: =C23/C5 -> 0.016937695 | D24: =D23/D5 -> 0.015299144 | E24: =E23/E5 -> 0.014472243 | F24: =F23/F5 -> 0.013926816 | G24: =G23/G5 -> 0.018454103 | H24: =H23/H5 -> 0.016862406 | I24: =I23/I5 -> 0.018133509 | J24: =J23/J5 -> 0.017803478 | ... M24: =M23/M5 -> 0.023473238
B26: EARNINGS BEFORE TAXES | C26: =IFERROR(C17-SUM(C20,C23),0) -> 51.76 | D26: =IFERROR(D17-SUM(D20,D23),0) -> 172.15 | E26: =IFERROR(E17-SUM(E20,E23),0) -> 450.64 | F26: =IFERROR(F17-SUM(F20,F23),0) -> 615.82 | G26: =IFERROR(G17-SUM(G20,G23),0) -> 536.87 | H26: =IFERROR(H17-SUM(H20,H23),0) -> 994.4 | I26: =IFERROR(I17-SUM(I20,I23),0) -> 819.03 | J26: =IFERROR(J17-SUM(J20,J23),0) -> 606.71 | ... M26: =IFERROR(M17-SUM(M20,M23),0) -> 941.35
B27: EBT % of sales | C27: =C26/C5 -> 0.015081629 | D27: =D26/D5 -> 0.04152866 | E27: =E26/E5 -> 0.089070906 | F27: =F26/F5 -> 0.098342069 | G27: =G26/G5 -> 0.092403044 | H27: =H26/H5 -> 0.14176511 | I27: =I26/I5 -> 0.11246318 | J27: =J26/J5 -> 0.07198153 | ... M27: =M26/M5 -> 0.089750337
B29: TAX | C29: =IFERROR('Data Sheet'!B29,0) -> 12.27 | D29: =IFERROR('Data Sheet'!C29,0) -> 77.25 | E29: =IFERROR('Data Sheet'!D29,0) -> 162.49 | F29: =IFERROR('Data Sheet'!E29,0) -> 237.11 | G29: =IFERROR('Data Sheet'!F29,0) -> 153.53 | H29: =IFERROR('Data Sheet'!G29,0) -> 283.15 | I29: =IFERROR('Data Sheet'!H29,0) -> 257.22 | J29: =IFERROR('Data Sheet'!I29,0) -> 197.94 | ... L29: =IFERROR('Data Sheet'!K29,0) -> 226.95 | M29: =IFERROR(SUM('Data Sheet'!H48:K48),0) -> 239.69
B30: Effective tax rate | C30: =C29/C26 -> 0.23705564 | D30: =D29/D26 -> 0.44873657 | E30: =E29/E26 -> 0.36057607 | F30: =F29/F26 -> 0.38503134 | G30: =G29/G26 -> 0.2859724 | H30: =H29/H26 -> 0.28474457 | I30: =I29/I26 -> 0.31405443 | J30: =J29/J26 -> 0.32625142 | ... M30: =M29/M26 -> 0.25462368
B32: NET PROFIT | C32: =C26-C29 -> 39.49 | D32: =D26-D29 -> 94.9 | E32: =E26-E29 -> 288.15 | F32: =F26-F29 -> 378.71 | G32: =G26-G29 -> 383.34 | H32: =H26-H29 -> 711.25 | I32: =I26-I29 -> 561.81 | J32: =J26-J29 -> 408.77 | ... M32: =M26-M29 -> 701.66
B33: Net margin | C33: =C32/C5 -> 0.011506444 | D33: =D32/D5 -> 0.022893232 | E33: =E32/E5 -> 0.056954069 | F33: =F32/F5 -> 0.06047729 | G33: =G32/G5 -> 0.065978324 | H33: =H32/H5 -> 0.10139826 | I33: =I32/I5 -> 0.077143622 | J33: =J32/J5 -> 0.048497453 | ... M33: =M32/M5 -> 0.066897776
B35: NO OF EQUITY SHARES | C35: =IFERROR('Data Sheet'!B93,0) -> 12.26 | D35: =IFERROR('Data Sheet'!C93,0) -> 12.26 | E35: =IFERROR('Data Sheet'!D93,0) -> 12.26 | F35: =IFERROR('Data Sheet'!E93,0) -> 12.26 | G35: =IFERROR('Data Sheet'!F93,0) -> 12.26 | H35: =IFERROR('Data Sheet'!G93,0) -> 13.48 | I35: =IFERROR('Data Sheet'!H93,0) -> 13.19 | J35: =IFERROR('Data Sheet'!I93,0) -> 13.19 | ... L35: =IFERROR('Data Sheet'!K93,0) -> 11.19
B37: EPS | C37: =IFERROR(C32/C35,0) -> 3.221044 | D37: =IFERROR(D32/D35,0) -> 7.7406199 | E37: =IFERROR(E32/E35,0) -> 23.503263 | F37: =IFERROR(F32/F35,0) -> 30.889886 | G37: =IFERROR(G32/G35,0) -> 31.267537 | H37: =IFERROR(H32/H35,0) -> 52.763353 | I37: =IFERROR(I32/I35,0) -> 42.593632 | J37: =IFERROR(J32/J35,0) -> 30.990902 | ... M37: =IFERROR(M32/M35,0) -> 0
B38: EPS % of growth | D38: =D37/C37-1 -> 1.40314 | E38: =E37/D37-1 -> 2.0363541 | F38: =F37/E37-1 -> 0.31428076 | G38: =G37/F37-1 -> 0.012225714 | H38: =H37/G37-1 -> 0.68748033 | I38: =I37/H37-1 -> -0.19274214 | J38: =J37/I37-1 -> -0.27240526 | K38: =K37/J37-1 -> 0.60972654 | ... M38: =M37/L37-1 -> -1
B40: DIVIDEND PER SHARE | C40: =IFERROR('Data Sheet'!B31/'HISTORICAL FS'!C35,0) -> 1.1998369 | D40: =IFERROR('Data Sheet'!C31/'HISTORICAL FS'!D35,0) -> 1.5 | E40: =IFERROR('Data Sheet'!D31/'HISTORICAL FS'!E35,0) -> 2 | F40: =IFERROR('Data Sheet'!E31/'HISTORICAL FS'!F35,0) -> 2.4991843 | G40: =IFERROR('Data Sheet'!F31/'HISTORICAL FS'!G35,0) -> 2.4991843 | H40: =IFERROR('Data Sheet'!G31/'HISTORICAL FS'!H35,0) -> 7.5014837 | I40: =IFERROR('Data Sheet'!H31/'HISTORICAL FS'!I35,0) -> 7.0022745 | J40: =IFERROR('Data Sheet'!I31/'HISTORICAL FS'!J35,0) -> 7.0022745 | ... M40: =IFERROR('Data Sheet'!L31/'HISTORICAL FS'!M35,0) -> 0
B41: Divident payout ratio | C41: =IFERROR(C40/C37,0) -> 0.37249937 | D41: =IFERROR(D40/D37,0) -> 0.19378293 | E41: =IFERROR(E40/E37,0) -> 0.085094569 | F41: =IFERROR(F40/F37,0) -> 0.080906234 | G41: =IFERROR(G40/G37,0) -> 0.079929045 | H41: =IFERROR(H40/H37,0) -> 0.14217223 | I41: =IFERROR(I40/I37,0) -> 0.16439722 | J41: =IFERROR(J40/J37,0) -> 0.22594613 | ... M41: =IFERROR(M40/M37,0) -> 0
B43: RETAINED EARNINGS | C43: =IFERROR(1-C41,0) -> 0.62750063 | D43: =IFERROR(1-D41,0) -> 0.80621707 | E43: =IFERROR(1-E41,0) -> 0.91490543 | F43: =IFERROR(1-F41,0) -> 0.91909377 | G43: =IFERROR(1-G41,0) -> 0.92007096 | H43: =IFERROR(1-H41,0) -> 0.85782777 | I43: =IFERROR(1-I41,0) -> 0.83560278 | J43: =IFERROR(1-J41,0) -> 0.77405387 | ... M43: =IFERROR(1-M41,0) -> 1
A45: # | B45: BALANCE SHEET
B46: Equity share capital | C46: =IFERROR('Data Sheet'!B57,0) -> 122.58 | D46: =IFERROR('Data Sheet'!C57,0) -> 122.58 | E46: =IFERROR('Data Sheet'!D57,0) -> 122.58 | F46: =IFERROR('Data Sheet'!E57,0) -> 122.58 | G46: =IFERROR('Data Sheet'!F57,0) -> 122.58 | H46: =IFERROR('Data Sheet'!G57,0) -> 134.83 | I46: =IFERROR('Data Sheet'!H57,0) -> 131.94 | J46: =IFERROR('Data Sheet'!I57,0) -> 131.94 | ... M46: =IFERROR('Data Sheet'!L57,0) -> 0
B47: Reserves | C47: =IFERROR('Data Sheet'!B58,0) -> 1343.9 | D47: =IFERROR('Data Sheet'!C58,0) -> 1498.35 | E47: =IFERROR('Data Sheet'!D58,0) -> 2092.56 | F47: =IFERROR('Data Sheet'!E58,0) -> 2550.91 | G47: =IFERROR('Data Sheet'!F58,0) -> 2994.82 | H47: =IFERROR('Data Sheet'!G58,0) -> 4891.3 | I47: =IFERROR('Data Sheet'!H58,0) -> 7467.96 | J47: =IFERROR('Data Sheet'!I58,0) -> 8054.77 | ... M47: =IFERROR('Data Sheet'!L58,0) -> 0
B48: Borrowings | C48: =IFERROR('Data Sheet'!B59,0) -> 368.12 | D48: =IFERROR('Data Sheet'!C59,0) -> 265.43 | E48: =IFERROR('Data Sheet'!D59,0) -> 51.09 | F48: =IFERROR('Data Sheet'!E59,0) -> 280.96 | G48: =IFERROR('Data Sheet'!F59,0) -> 47.67 | H48: =IFERROR('Data Sheet'!G59,0) -> 60.61 | I48: =IFERROR('Data Sheet'!H59,0) -> 51.95 | J48: =IFERROR('Data Sheet'!I59,0) -> 57.3 | ... M48: =IFERROR('Data Sheet'!L59,0) -> 0
B49: Other Liabilities | C49: =IFERROR('Data Sheet'!B60,0) -> 1133.58 | D49: =IFERROR('Data Sheet'!C60,0) -> 1312.86 | E49: =IFERROR('Data Sheet'!D60,0) -> 1706.3 | F49: =IFERROR('Data Sheet'!E60,0) -> 1752.52 | G49: =IFERROR('Data Sheet'!F60,0) -> 1848.89 | H49: =IFERROR('Data Sheet'!G60,0) -> 1791.43 | I49: =IFERROR('Data Sheet'!H60,0) -> 1455.89 | J49: =IFERROR('Data Sheet'!I60,0) -> 1840.81 | ... M49: =IFERROR('Data Sheet'!L60,0) -> 0
B50: Total Liabilities | C50: =IFERROR('Data Sheet'!B61,0) -> 2968.18 | D50: =IFERROR('Data Sheet'!C61,0) -> 3199.22 | E50: =IFERROR('Data Sheet'!D61,0) -> 3972.53 | F50: =IFERROR('Data Sheet'!E61,0) -> 4706.97 | G50: =IFERROR('Data Sheet'!F61,0) -> 5013.96 | H50: =IFERROR('Data Sheet'!G61,0) -> 6878.17 | I50: =IFERROR('Data Sheet'!H61,0) -> 9107.74 | J50: =IFERROR('Data Sheet'!I61,0) -> 10084.82 | ... M50: =IFERROR('Data Sheet'!L61,0) -> 0
B52: Fixed Assets net block | C52: =IFERROR('Data Sheet'!B62,0) -> 1539.02 | D52: =IFERROR('Data Sheet'!C62,0) -> 1581.14 | E52: =IFERROR('Data Sheet'!D62,0) -> 1587.8 | F52: =IFERROR('Data Sheet'!E62,0) -> 1647.23 | G52: =IFERROR('Data Sheet'!F62,0) -> 1702.41 | H52: =IFERROR('Data Sheet'!G62,0) -> 1796.23 | I52: =IFERROR('Data Sheet'!H62,0) -> 1841.05 | J52: =IFERROR('Data Sheet'!I62,0) -> 1891.15 | ... M52: =IFERROR('Data Sheet'!L62,0) -> 0
B53: Capital work in progress | C53: =IFERROR('Data Sheet'!B63,0) -> 58.43 | D53: =IFERROR('Data Sheet'!C63,0) -> 34.7 | E53: =IFERROR('Data Sheet'!D63,0) -> 65.72 | F53: =IFERROR('Data Sheet'!E63,0) -> 79.96 | G53: =IFERROR('Data Sheet'!F63,0) -> 124.66 | H53: =IFERROR('Data Sheet'!G63,0) -> 64.69 | I53: =IFERROR('Data Sheet'!H63,0) -> 87.8 | J53: =IFERROR('Data Sheet'!I63,0) -> 113.68 | ... M53: =IFERROR('Data Sheet'!L63,0) -> 0
B54: Investments | C54: =IFERROR('Data Sheet'!B64,0) -> 63.66 | D54: =IFERROR('Data Sheet'!C64,0) -> 212.34 | E54: =IFERROR('Data Sheet'!D64,0) -> 549.04 | F54: =IFERROR('Data Sheet'!E64,0) -> 490.79 | G54: =IFERROR('Data Sheet'!F64,0) -> 797.36 | H54: =IFERROR('Data Sheet'!G64,0) -> 1938.02 | I54: =IFERROR('Data Sheet'!H64,0) -> 4835.84 | J54: =IFERROR('Data Sheet'!I64,0) -> 4766.69 | ... M54: =IFERROR('Data Sheet'!L64,0) -> 0
B55: Other Assets | C55: =IFERROR('Data Sheet'!B65-SUM('Data Sheet'!B67,'Data Sheet'!B68,'Data Sheet'!B69),0) -> 222.31 | D55: =IFERROR('Data Sheet'!C65-SUM('Data Sheet'!C67,'Data Sheet'!C68,'Data Sheet'!C69),0) -> 220.19 | E55: =IFERROR('Data Sheet'!D65-SUM('Data Sheet'!D67,'Data Sheet'!D68,'Data Sheet'!D69),0) -> 294.95 | F55: =IFERROR('Data Sheet'!E65-SUM('Data Sheet'!E67,'Data Sheet'!E68,'Data Sheet'!E69),0) -> 457.22 | G55: =IFERROR('Data Sheet'!F65-SUM('Data Sheet'!F67,'Data Sheet'!F68,'Data Sheet'!F69),0) -> 449.43 | H55: =IFERROR('Data Sheet'!G65-SUM('Data Sheet'!G67,'Data Sheet'!G68,'Data Sheet'!G69),0) -> 381.73 | I55: =IFERROR('Data Sheet'!H65-SUM('Data Sheet'!H67,'Data Sheet'!H68,'Data Sheet'!H69),0) -> 432.03 | J55: =IFERROR('Data Sheet'!I65-SUM('Data Sheet'!I67,'Data Sheet'!I68,'Data Sheet'!I69),0) -> 444.07 | ... M55: =IFERROR('Data Sheet'!L65-SUM('Data Sheet'!L67,'Data Sheet'!L68,'Data Sheet'!L69),0) -> 0
B56: Total non Current assets | C56: =IFERROR(SUM(C52,C53,C54,C55),0) -> 1883.42 | D56: =IFERROR(SUM(D52,D53,D54,D55),0) -> 2048.37 | E56: =IFERROR(SUM(E52,E53,E54,E55),0) -> 2497.51 | F56: =IFERROR(SUM(F52,F53,F54,F55),0) -> 2675.2 | G56: =IFERROR(SUM(G52,G53,G54,G55),0) -> 3073.86 | H56: =IFERROR(SUM(H52,H53,H54,H55),0) -> 4180.67 | I56: =IFERROR(SUM(I52,I53,I54,I55),0) -> 7196.72 | J56: =IFERROR(SUM(J52,J53,J54,J55),0) -> 7215.59 | ... M56: =IFERROR(SUM(M52,M53,M54,M55),0) -> 0
B58: Receivables | C58: =IFERROR('Data Sheet'!B67,0) -> 374.97 | D58: =IFERROR('Data Sheet'!C67,0) -> 456.45 | E58: =IFERROR('Data Sheet'!D67,0) -> 592 | F58: =IFERROR('Data Sheet'!E67,0) -> 931.05 | G58: =IFERROR('Data Sheet'!F67,0) -> 731.86 | H58: =IFERROR('Data Sheet'!G67,0) -> 657.58 | I58: =IFERROR('Data Sheet'!H67,0) -> 792.62 | J58: =IFERROR('Data Sheet'!I67,0) -> 1179.65 | ... M58: =IFERROR('Data Sheet'!L67,0) -> 0
B59: Inventory | C59: =IFERROR('Data Sheet'!B68,0) -> 456.76 | D59: =IFERROR('Data Sheet'!C68,0) -> 450.3 | E59: =IFERROR('Data Sheet'!D68,0) -> 565.73 | F59: =IFERROR('Data Sheet'!E68,0) -> 857.42 | G59: =IFERROR('Data Sheet'!F68,0) -> 883.36 | H59: =IFERROR('Data Sheet'!G68,0) -> 718.16 | I59: =IFERROR('Data Sheet'!H68,0) -> 846.56 | J59: =IFERROR('Data Sheet'!I68,0) -> 1217.68 | ... M59: =IFERROR('Data Sheet'!L68,0) -> 0
B60: Cash and Bank | C60: =IFERROR('Data Sheet'!B69,0) -> 253.03 | D60: =IFERROR('Data Sheet'!C69,0) -> 244.1 | E60: =IFERROR('Data Sheet'!D69,0) -> 317.29 | F60: =IFERROR('Data Sheet'!E69,0) -> 243.3 | G60: =IFERROR('Data Sheet'!F69,0) -> 324.88 | H60: =IFERROR('Data Sheet'!G69,0) -> 1321.76 | I60: =IFERROR('Data Sheet'!H69,0) -> 271.84 | J60: =IFERROR('Data Sheet'!I69,0) -> 471.9 | ... M60: =IFERROR('Data Sheet'!L69,0) -> 0
B61: Total Current Assets | C61: =IFERROR(SUM('Data Sheet'!B67,'Data Sheet'!B68,'Data Sheet'!B69),0) -> 1084.76 | D61: =IFERROR(SUM('Data Sheet'!C67,'Data Sheet'!C68,'Data Sheet'!C69),0) -> 1150.85 | E61: =IFERROR(SUM('Data Sheet'!D67,'Data Sheet'!D68,'Data Sheet'!D69),0) -> 1475.02 | F61: =IFERROR(SUM('Data Sheet'!E67,'Data Sheet'!E68,'Data Sheet'!E69),0) -> 2031.77 | G61: =IFERROR(SUM('Data Sheet'!F67,'Data Sheet'!F68,'Data Sheet'!F69),0) -> 1940.1 | H61: =IFERROR(SUM('Data Sheet'!G67,'Data Sheet'!G68,'Data Sheet'!G69),0) -> 2697.5 | I61: =IFERROR(SUM('Data Sheet'!H67,'Data Sheet'!H68,'Data Sheet'!H69),0) -> 1911.02 | J61: =IFERROR(SUM('Data Sheet'!I67,'Data Sheet'!I68,'Data Sheet'!I69),0) -> 2869.23 | ... M61: =IFERROR(SUM('Data Sheet'!L67,'Data Sheet'!L68,'Data Sheet'!L69),0) -> 0
B63: Total Assets | C63: =IFERROR(SUM(C56,C61),0) -> 2968.18 | D63: =IFERROR(SUM(D56,D61),0) -> 3199.22 | E63: =IFERROR(SUM(E56,E61),0) -> 3972.53 | F63: =IFERROR(SUM(F56,F61),0) -> 4706.97 | G63: =IFERROR(SUM(G56,G61),0) -> 5013.96 | H63: =IFERROR(SUM(H56,H61),0) -> 6878.17 | I63: =IFERROR(SUM(I56,I61),0) -> 9107.74 | J63: =IFERROR(SUM(J56,J61),0) -> 10084.82 | ... M63: =IFERROR(SUM(M56,M61),0) -> 0
B65: CHECK | C65: =C63=C50 -> TRUE | D65: =D63=D50 -> TRUE | E65: =E63=E50 -> TRUE | F65: =F63=F50 -> TRUE | G65: =G63=G50 -> TRUE | H65: =H63=H50 -> TRUE | I65: =I63=I50 -> TRUE | J65: =J63=J50 -> TRUE | ... M65: =M63=M50 -> TRUE
A67: #CASH FLOW STATEMENT | B67: CASH FLOW STATEMENT
B68: operating activities
B69: Profit from operations | C69: =IFERROR(CFS!D3,0) -> 178 | D69: =IFERROR(CFS!E3,0) -> 305 | E69: =IFERROR(CFS!F3,0) -> 578 | F69: =IFERROR(CFS!G3,0) -> 727 | G69: =IFERROR(CFS!H3,0) -> 647 | H69: =IFERROR(CFS!I3,0) -> 1111 | I69: =IFERROR(CFS!J3,0) -> 936 | J69: =IFERROR(CFS!K3,0) -> 815 | ... M69: =IFERROR(CFS!N3,0) -> 0
B70: Receivables | C70: =IFERROR(CFS!D4,0) -> -15 | D70: =IFERROR(CFS!E4,0) -> -79 | E70: =IFERROR(CFS!F4,0) -> -143 | F70: =IFERROR(CFS!G4,0) -> -324 | G70: =IFERROR(CFS!H4,0) -> 170 | H70: =IFERROR(CFS!I4,0) -> 47 | I70: =IFERROR(CFS!J4,0) -> -142 | J70: =IFERROR(CFS!K4,0) -> -384 | ... M70: =IFERROR(CFS!N4,0) -> 0
B71: Inventory | C71: =IFERROR(CFS!D5,0) -> 22 | D71: =IFERROR(CFS!E5,0) -> -57 | E71: =IFERROR(CFS!F5,0) -> -123 | F71: =IFERROR(CFS!G5,0) -> -275 | G71: =IFERROR(CFS!H5,0) -> 0 | H71: =IFERROR(CFS!I5,0) -> 148 | I71: =IFERROR(CFS!J5,0) -> -129 | J71: =IFERROR(CFS!K5,0) -> -355 | ... M71: =IFERROR(CFS!N5,0) -> 0
B72: Payables | C72: =IFERROR(CFS!D6,0) -> 42 | D72: =IFERROR(CFS!E6,0) -> 155 | E72: =IFERROR(CFS!F6,0) -> 347 | F72: =IFERROR(CFS!G6,0) -> -1 | G72: =IFERROR(CFS!H6,0) -> 87 | H72: =IFERROR(CFS!I6,0) -> -20 | I72: =IFERROR(CFS!J6,0) -> -255 | J72: =IFERROR(CFS!K6,0) -> 357 | ... M72: =IFERROR(CFS!N6,0) -> 0
B73: Working capital changes | C73: =IFERROR(CFS!D7,0) -> -13 | D73: =IFERROR(CFS!E7,0) -> 21 | E73: =IFERROR(CFS!F7,0) -> -85 | F73: =IFERROR(CFS!G7,0) -> -152 | G73: =IFERROR(CFS!H7,0) -> 86 | H73: =IFERROR(CFS!I7,0) -> 86 | I73: =IFERROR(CFS!J7,0) -> -116 | J73: =IFERROR(CFS!K7,0) -> -10 | ... M73: =IFERROR(CFS!N7,0) -> 0
B74: Direct taxes | C74: =IFERROR(CFS!D8,0) -> 36 | D74: =IFERROR(CFS!E8,0) -> 40 | E74: =IFERROR(CFS!F8,0) -> -4 | F74: =IFERROR(CFS!G8,0) -> -751 | G74: =IFERROR(CFS!H8,0) -> 344 | H74: =IFERROR(CFS!I8,0) -> 261 | I74: =IFERROR(CFS!J8,0) -> -641 | J74: =IFERROR(CFS!K8,0) -> -392 | ... M74: =IFERROR(CFS!N8,0) -> 0
B75: Other opearting items | C75: - | D75: - | E75: - | F75: - | G75: - | H75: - | I75: - | J75: - | K75: - | L75: - | M75: -
B76: CASH FROM OPERATING ACTIVITES | C76: =SUM(C69:C74) -> 250 | D76: =SUM(D69:D74) -> 385 | E76: =SUM(E69:E74) -> 570 | F76: =SUM(F69:F74) -> -776 | G76: =SUM(G69:G74) -> 1334 | H76: =SUM(H69:H74) -> 1633 | I76: =SUM(I69:I74) -> -347 | J76: =SUM(J69:J74) -> 31 | ... M76: =SUM(M69:M74) -> 0
B78: Investing activities
B79: Fixed asset purchased | C79: =IFERROR(CFS!D11,0) -> -54 | D79: =IFERROR(CFS!E11,0) -> -78 | E79: =IFERROR(CFS!F11,0) -> -115 | F79: =IFERROR(CFS!G11,0) -> -150 | G79: =IFERROR(CFS!H11,0) -> -195 | H79: =IFERROR(CFS!I11,0) -> -123 | I79: =IFERROR(CFS!J11,0) -> -186 | J79: =IFERROR(CFS!K11,0) -> -219 | ... M79: =IFERROR(CFS!N11,0) -> 0
B80: Fixed asset sold | C80: =IFERROR(CFS!D12,0) -> 2 | D80: =IFERROR(CFS!E12,0) -> 13 | E80: =IFERROR(CFS!F12,0) -> 14 | F80: =IFERROR(CFS!G12,0) -> 11 | G80: =IFERROR(CFS!H12,0) -> 5 | H80: =IFERROR(CFS!I12,0) -> 9 | I80: =IFERROR(CFS!J12,0) -> 32 | J80: =IFERROR(CFS!K12,0) -> 5 | ... M80: =IFERROR(CFS!N12,0) -> 0
B81: Investments purchased | C81: =IFERROR(CFS!D13,0) -> 0 | D81: =IFERROR(CFS!E13,0) -> -160 | E81: =IFERROR(CFS!F13,0) -> -298 | F81: =IFERROR(CFS!G13,0) -> 0 | G81: =IFERROR(CFS!H13,0) -> -211 | H81: =IFERROR(CFS!I13,0) -> -978 | I81: =IFERROR(CFS!J13,0) -> -2851 | J81: =IFERROR(CFS!K13,0) -> -423 | ... M81: =IFERROR(CFS!N13,0) -> 0
B82: Investments solds | C82: =IFERROR(CFS!D14,0) -> 0 | D82: =IFERROR(CFS!E14,0) -> 0 | E82: =IFERROR(CFS!F14,0) -> 3 | F82: =IFERROR(CFS!G14,0) -> 178 | G82: =IFERROR(CFS!H14,0) -> 0 | H82: =IFERROR(CFS!I14,0) -> 0 | I82: =IFERROR(CFS!J14,0) -> 31 | J82: =IFERROR(CFS!K14,0) -> 667 | ... M82: =IFERROR(CFS!N14,0) -> 0
B83: Interest received | C83: =IFERROR(CFS!D15,0) -> 30 | D83: =IFERROR(CFS!E15,0) -> 29 | E83: =IFERROR(CFS!F15,0) -> 25 | F83: =IFERROR(CFS!G15,0) -> 35 | G83: =IFERROR(CFS!H15,0) -> 43 | H83: =IFERROR(CFS!I15,0) -> 45 | I83: =IFERROR(CFS!J15,0) -> 105 | J83: =IFERROR(CFS!K15,0) -> 11 | ... M83: =IFERROR(CFS!N15,0) -> 0
B84: Dividends received | C84: =IFERROR(CFS!D16,0) -> 0 | D84: =IFERROR(CFS!E16,0) -> 0 | E84: =IFERROR(CFS!F16,0) -> 0 | F84: =IFERROR(CFS!G16,0) -> 0 | G84: =IFERROR(CFS!H16,0) -> 0 | H84: =IFERROR(CFS!I16,0) -> 0 | I84: =IFERROR(CFS!J16,0) -> 0 | J84: =IFERROR(CFS!K16,0) -> 0 | ... M84: =IFERROR(CFS!N16,0) -> 0
B85: Other investing items | C85: =IFERROR(CFS!D19,0) -> -4 | D85: =IFERROR(CFS!E19,0) -> 56 | E85: =IFERROR(CFS!F19,0) -> 10 | F85: =IFERROR(CFS!G19,0) -> 17 | G85: =IFERROR(CFS!H19,0) -> -9 | H85: =IFERROR(CFS!I19,0) -> -1031 | I85: =IFERROR(CFS!J19,0) -> 1017 | J85: =IFERROR(CFS!K19,0) -> -110 | ... M85: =IFERROR(CFS!N19,0) -> 0
B86: CASH FLOW FROM INVESTING ACTIVITES | C86: =IFERROR(SUM(C79:C85),0) -> -26 | D86: =IFERROR(SUM(D79:D85),0) -> -140 | E86: =IFERROR(SUM(E79:E85),0) -> -361 | F86: =IFERROR(SUM(F79:F85),0) -> 91 | G86: =IFERROR(SUM(G79:G85),0) -> -367 | H86: =IFERROR(SUM(H79:H85),0) -> -2078 | I86: =IFERROR(SUM(I79:I85),0) -> -1852 | J86: =IFERROR(SUM(J79:J85),0) -> -69 | ... M86: =IFERROR(SUM(M79:M85),0) -> 0
B88: Financing activities
B89: Proceeds from shares | C89: =IFERROR(CFS!D21,0) -> 1 | D89: =IFERROR(CFS!E21,0) -> 1 | E89: =IFERROR(CFS!F21,0) -> 0 | F89: =IFERROR(CFS!G21,0) -> 0 | G89: =IFERROR(CFS!H21,0) -> 0 | H89: =IFERROR(CFS!I21,0) -> 1058 | I89: =IFERROR(CFS!J21,0) -> 1902 | J89: =IFERROR(CFS!K21,0) -> 21 | ... M89: =IFERROR(CFS!N21,0) -> 0
B90: Proceeds from borrowings | C90: =IFERROR(CFS!D22,0) -> 35 | D90: =IFERROR(CFS!E22,0) -> 17 | E90: =IFERROR(CFS!F22,0) -> 0 | F90: =IFERROR(CFS!G22,0) -> 269 | G90: =IFERROR(CFS!H22,0) -> 0 | H90: =IFERROR(CFS!I22,0) -> 0 | I90: =IFERROR(CFS!J22,0) -> 0 | J90: =IFERROR(CFS!K22,0) -> 0 | ... M90: =IFERROR(CFS!N22,0) -> 0
B91: Repayment of borrowings | C91: =IFERROR(CFS!D23,0) -> -173 | D91: =IFERROR(CFS!E23,0) -> -115 | E91: =IFERROR(CFS!F23,0) -> -213 | F91: =IFERROR(CFS!G23,0) -> -42 | G91: =IFERROR(CFS!H23,0) -> -270 | H91: =IFERROR(CFS!I23,0) -> -6 | I91: =IFERROR(CFS!J23,0) -> 0 | J91: =IFERROR(CFS!K23,0) -> 0 | ... M91: =IFERROR(CFS!N23,0) -> 0
B92: Interest paid fin | C92: =IFERROR(CFS!D24,0) -> -45 | D92: =IFERROR(CFS!E24,0) -> -28 | E92: =IFERROR(CFS!F24,0) -> -21 | F92: =IFERROR(CFS!G24,0) -> -13 | G92: =IFERROR(CFS!H24,0) -> -9 | H92: =IFERROR(CFS!I24,0) -> -8 | I92: =IFERROR(CFS!J24,0) -> -10 | J92: =IFERROR(CFS!K24,0) -> -8 | ... M92: =IFERROR(CFS!N24,0) -> 0
B93: Dividends paid | C93: =IFERROR(CFS!D25,0) -> -13 | D93: =IFERROR(CFS!E25,0) -> -13 | E93: =IFERROR(CFS!F25,0) -> -16 | F93: =IFERROR(CFS!G25,0) -> -22 | G93: =IFERROR(CFS!H25,0) -> -26 | H93: =IFERROR(CFS!I25,0) -> -25 | I93: =IFERROR(CFS!J25,0) -> -74 | J93: =IFERROR(CFS!K25,0) -> -76 | ... M93: =IFERROR(CFS!N25,0) -> 0
B94: Financial liabilities | C94: =IFERROR(CFS!D26,0) -> 0 | D94: =IFERROR(CFS!E26,0) -> 0 | E94: =IFERROR(CFS!F26,0) -> 0 | F94: =IFERROR(CFS!G26,0) -> 0 | G94: =IFERROR(CFS!H26,0) -> -3 | H94: =IFERROR(CFS!I26,0) -> -5 | I94: =IFERROR(CFS!J26,0) -> -6 | J94: =IFERROR(CFS!K26,0) -> -7 | ... M94: =IFERROR(CFS!N26,0) -> 0
B95: Other financing items | C95: =IFERROR(CFS!D27,0) -> 0 | D95: =IFERROR(CFS!E27,0) -> 0 | E95: =IFERROR(CFS!F27,0) -> 250 | F95: =IFERROR(CFS!G27,0) -> 0 | G95: =IFERROR(CFS!H27,0) -> 0 | H95: =IFERROR(CFS!I27,0) -> 0 | I95: =IFERROR(CFS!J27,0) -> 0 | J95: =IFERROR(CFS!K27,0) -> 0 | ... M95: =IFERROR(CFS!N27,0) -> 0
B96: Cash from financing activites | C96: =IFERROR(SUM(C89:C95),0) -> -195 | D96: =IFERROR(SUM(D89:D95),0) -> -138 | E96: =IFERROR(SUM(E89:E95),0) -> 0 | F96: =IFERROR(SUM(F89:F95),0) -> 192 | G96: =IFERROR(SUM(G89:G95),0) -> -308 | H96: =IFERROR(SUM(H89:H95),0) -> 1014 | I96: =IFERROR(SUM(I89:I95),0) -> 1812 | J96: =IFERROR(SUM(J89:J95),0) -> -70 | ... M96: =IFERROR(SUM(M89:M95),0) -> 0
B98: NET CASH FLOW | C98: =IFERROR(SUM(C76,C86,C96),0) -> 29 | D98: =IFERROR(SUM(D76,D86,D96),0) -> 107 | E98: =IFERROR(SUM(E76,E86,E96),0) -> 209 | F98: =IFERROR(SUM(F76,F86,F96),0) -> -493 | G98: =IFERROR(SUM(G76,G86,G96),0) -> 659 | H98: =IFERROR(SUM(H76,H86,H96),0) -> 569 | I98: =IFERROR(SUM(I76,I86,I96),0) -> -387 | J98: =IFERROR(SUM(J76,J86,J96),0) -> -108 | ... M98: =IFERROR(SUM(M76,M86,M96),0) -> 0

Sheet RATIO ANALYSIS
E1: ="RATIO ANALYSIS OF - "&'Data Sheet'!B1 -> RATIO ANALYSIS OF - ESCORTS KUBOTA LTD
A2: YEARS | B2: ='Data Sheet'!B16 -> 42460 | C2: ='Data Sheet'!C16 -> 42825 | D2: ='Data Sheet'!D16 -> 43190 | E2: ='Data Sheet'!E16 -> 43555 | F2: ='Data Sheet'!F16 -> 43921 | G2: ='Data Sheet'!G16 -> 44286 | H2: ='Data Sheet'!H16 -> 44651 | I2: ='Data Sheet'!I16 -> 45016 | ... K2: ='Data Sheet'!K16 -> 45747 | L2: TREND LINE | M2: MEAN | N2: MEDIAN
A4: Sales Growth | B4: =IFERROR('HISTORICAL FS'!C6,0) -> - | C4: =IFERROR('HISTORICAL FS'!D6,0) -> 0.20785026 | D4: =IFERROR('HISTORICAL FS'!E6,0) -> 0.22049149 | E4: =IFERROR('HISTORICAL FS'!F6,0) -> 0.2377148 | F4: =IFERROR('HISTORICAL FS'!G6,0) -> -0.072170003 | G4: =IFERROR('HISTORICAL FS'!H6,0) -> 0.2072825 | H4: =IFERROR('HISTORICAL FS'!I6,0) -> 0.038239797 | I4: =IFERROR('HISTORICAL FS'!J6,0) -> 0.15736579 | ... K4: =IFERROR('HISTORICAL FS'!L6,0) -> 0.044911099 | M4: =IFERROR(AVERAGE(C4:K4),0) -> 0.13386746 | N4: =IFERROR(MEDIAN(C4:K4),0) -> 0.16312143
A5: EBITDA Growth | B5: - | C5: =IFERROR('HISTORICAL FS'!E17/'HISTORICAL FS'!D17-1,0) -> 1.0664351 | D5: =IFERROR('HISTORICAL FS'!F17/'HISTORICAL FS'!E17-1,0) -> 0.30581007 | E5: =IFERROR('HISTORICAL FS'!G17/'HISTORICAL FS'!F17-1,0) -> -0.084766874 | F5: =IFERROR('HISTORICAL FS'!H17/'HISTORICAL FS'!G17-1,0) -> 0.70268554 | G5: =IFERROR('HISTORICAL FS'!I17/'HISTORICAL FS'!H17-1,0) -> -0.14205787 | H5: =IFERROR('HISTORICAL FS'!J17/'HISTORICAL FS'!I17-1,0) -> -0.20290665 | I5: =IFERROR('HISTORICAL FS'!K17/'HISTORICAL FS'!J17-1,0) -> 0.46793673 | J5: =IFERROR('HISTORICAL FS'!L17/'HISTORICAL FS'!K17-1,0) -> 0.029919407 | K5: =IFERROR('HISTORICAL FS'!M17/'HISTORICAL FS'!L17-1,0) -> 0.04514727 | M5: =IFERROR(AVERAGE(C5:K5),0) -> 0.24313364 | N5: =IFERROR(MEDIAN(C5:K5),0) -> 0.04514727
A6: EBIT Growth | B6: - | C6: =IFERROR('HISTORICAL FS'!E26/'HISTORICAL FS'!D26-1,0) -> 1.6177171 | D6: =IFERROR('HISTORICAL FS'!F26/'HISTORICAL FS'!E26-1,0) -> 0.36654536 | E6: =IFERROR('HISTORICAL FS'!G26/'HISTORICAL FS'!F26-1,0) -> -0.12820305 | F6: =IFERROR('HISTORICAL FS'!H26/'HISTORICAL FS'!G26-1,0) -> 0.85221748 | G6: =IFERROR('HISTORICAL FS'!I26/'HISTORICAL FS'!H26-1,0) -> -0.1763576 | H6: =IFERROR('HISTORICAL FS'!J26/'HISTORICAL FS'!I26-1,0) -> -0.25923348 | I6: =IFERROR('HISTORICAL FS'!K26/'HISTORICAL FS'!J26-1,0) -> 0.42514546 | J6: =IFERROR('HISTORICAL FS'!L26/'HISTORICAL FS'!K26-1,0) -> 0.030902677 | K6: =IFERROR('HISTORICAL FS'!M26/'HISTORICAL FS'!L26-1,0) -> 0.056070992 | M6: =IFERROR(AVERAGE(C6:K6),0) -> 0.30942277 | N6: =IFERROR(MEDIAN(C6:K6),0) -> 0.056070992
A7: Net profit Growth | B7: - | C7: =IFERROR('HISTORICAL FS'!E32/'HISTORICAL FS'!D32-1,0) -> 2.0363541 | D7: =IFERROR('HISTORICAL FS'!F32/'HISTORICAL FS'!E32-1,0) -> 0.31428076 | E7: =IFERROR('HISTORICAL FS'!G32/'HISTORICAL FS'!F32-1,0) -> 0.012225714 | F7: =IFERROR('HISTORICAL FS'!H32/'HISTORICAL FS'!G32-1,0) -> 0.85540251 | G7: =IFERROR('HISTORICAL FS'!I32/'HISTORICAL FS'!H32-1,0) -> -0.21010896 | H7: =IFERROR('HISTORICAL FS'!J32/'HISTORICAL FS'!I32-1,0) -> -0.27240526 | I7: =IFERROR('HISTORICAL FS'!K32/'HISTORICAL FS'!J32-1,0) -> 0.34855787 | J7: =IFERROR('HISTORICAL FS'!L32/'HISTORICAL FS'!K32-1,0) -> 0.20529705 | K7: =IFERROR('HISTORICAL FS'!M32/'HISTORICAL FS'!L32-1,0) -> 0.056048885 | M7: =IFERROR(AVERAGE(C7:K7),0) -> 0.37173918 | N7: =IFERROR(MEDIAN(C7:K7),0) -> 0.20529705
A8: Dividend Growth | B8: - | C8: =IFERROR('HISTORICAL FS'!D40/'HISTORICAL FS'!C40-1,0) -> 0.25016995 | D8: =IFERROR('HISTORICAL FS'!E40/'HISTORICAL FS'!D40-1,0) -> 0.33333333 | E8: =IFERROR('HISTORICAL FS'!F40/'HISTORICAL FS'!E40-1,0) -> 0.24959217 | F8: =IFERROR('HISTORICAL FS'!G40/'HISTORICAL FS'!F40-1,0) -> 0 | G8: =IFERROR('HISTORICAL FS'!H40/'HISTORICAL FS'!G40-1,0) -> 2.0015728 | H8: =IFERROR('HISTORICAL FS'!I40/'HISTORICAL FS'!H40-1,0) -> -0.066548066 | I8: =IFERROR('HISTORICAL FS'!J40/'HISTORICAL FS'!I40-1,0) -> 0 | J8: =IFERROR('HISTORICAL FS'!K40/'HISTORICAL FS'!J40-1,0) -> 1.5705933 | K8: =IFERROR('HISTORICAL FS'!L40/'HISTORICAL FS'!K40-1,0) -> 0.55525767 | M8: =IFERROR(AVERAGE(C8:K8),0) -> 0.54377457 | N8: =IFERROR(MEDIAN(C8:K8),0) -> 0.25016995
A10: Gross Margin | B10: =IFERROR('HISTORICAL FS'!C12,0) -> 0.14557735 | C10: =IFERROR('HISTORICAL FS'!D12,0) -> 0.17256768 | D10: =IFERROR('HISTORICAL FS'!E12,0) -> 0.19485546 | E10: =IFERROR('HISTORICAL FS'!F12,0) -> 0.19665539 | F10: =IFERROR('HISTORICAL FS'!G12,0) -> 0.20597443 | G10: =IFERROR('HISTORICAL FS'!H12,0) -> 0.22400427 | H10: =IFERROR('HISTORICAL FS'!I12,0) -> 0.20346028 | I10: =IFERROR('HISTORICAL FS'!J12,0) -> 0.16093723 | ... K10: =IFERROR('HISTORICAL FS'!L12,0) -> 0.17338059 | M10: =IFERROR(AVERAGE(B10:K10),0) -> 0.18545774 | N10: =IFERROR(AVERAGE(C10:L10),0) -> 0.18988889
A11: EBITDA Margin | B11: =IFERROR('HISTORICAL FS'!C18,0) -> 0.04689699 | C11: =IFERROR('HISTORICAL FS'!D18,0) -> 0.064597993 | D11: =IFERROR('HISTORICAL FS'!E18,0) -> 0.10937197 | E11: =IFERROR('HISTORICAL FS'!F18,0) -> 0.11538928 | F11: =IFERROR('HISTORICAL FS'!G18,0) -> 0.11382268 | G11: =IFERROR('HISTORICAL FS'!H18,0) -> 0.16052931 | H11: =IFERROR('HISTORICAL FS'!I18,0) -> 0.13265226 | I11: =IFERROR('HISTORICAL FS'!J18,0) -> 0.091359393 | ... K11: =IFERROR('HISTORICAL FS'!L18,0) -> 0.11364737 | M11: =IFERROR(AVERAGE(B11:K11),0) -> 0.10635689 | N11: =IFERROR(AVERAGE(C11:L11),0) -> 0.11296354
A12: EBIT Margin | B12: =IFERROR(('HISTORICAL FS'!C17-'HISTORICAL FS'!C23)/'HISTORICAL FS'!C5,0) -> 0.029959295 | C12: =IFERROR(('HISTORICAL FS'!D17-'HISTORICAL FS'!D23)/'HISTORICAL FS'!D5,0) -> 0.04929885 | D12: =IFERROR(('HISTORICAL FS'!E17-'HISTORICAL FS'!E23)/'HISTORICAL FS'!E5,0) -> 0.09489973 | E12: =IFERROR(('HISTORICAL FS'!F17-'HISTORICAL FS'!F23)/'HISTORICAL FS'!F5,0) -> 0.10146247 | F12: =IFERROR(('HISTORICAL FS'!G17-'HISTORICAL FS'!G23)/'HISTORICAL FS'!G5,0) -> 0.095368574 | G12: =IFERROR(('HISTORICAL FS'!H17-'HISTORICAL FS'!H23)/'HISTORICAL FS'!H5,0) -> 0.1436669 | H12: =IFERROR(('HISTORICAL FS'!I17-'HISTORICAL FS'!I23)/'HISTORICAL FS'!I5,0) -> 0.11451875 | I12: =IFERROR(('HISTORICAL FS'!J17-'HISTORICAL FS'!J23)/'HISTORICAL FS'!J5,0) -> 0.073555914 | ... K12: =IFERROR(('HISTORICAL FS'!L17-'HISTORICAL FS'!L23)/'HISTORICAL FS'!L5,0) -> 0.089862435 | M12: =IFERROR(AVERAGE(B12:K12),0) -> 0.088503967 | N12: =IFERROR(AVERAGE(C12:L12),0) -> 0.09500893
A13: EBT Margin | B13: =IFERROR('HISTORICAL FS'!C27,0) -> 0.015081629 | C13: =IFERROR('HISTORICAL FS'!D27,0) -> 0.04152866 | D13: =IFERROR('HISTORICAL FS'!E27,0) -> 0.089070906 | E13: =IFERROR('HISTORICAL FS'!F27,0) -> 0.098342069 | F13: =IFERROR('HISTORICAL FS'!G27,0) -> 0.092403044 | G13: =IFERROR('HISTORICAL FS'!H27,0) -> 0.14176511 | H13: =IFERROR('HISTORICAL FS'!I27,0) -> 0.11246318 | I13: =IFERROR('HISTORICAL FS'!J27,0) -> 0.07198153 | ... K13: =IFERROR('HISTORICAL FS'!L27,0) -> 0.087014881 | M13: =IFERROR(AVERAGE(B13:K13),0) -> 0.083784829 | N13: =IFERROR(AVERAGE(C13:L13),0) -> 0.091418518
A14: Net profit margin | B14: =IFERROR('HISTORICAL FS'!C33,0) -> 0.011506444 | C14: =IFERROR('HISTORICAL FS'!D33,0) -> 0.022893232 | D14: =IFERROR('HISTORICAL FS'!E33,0) -> 0.056954069 | E14: =IFERROR('HISTORICAL FS'!F33,0) -> 0.06047729 | F14: =IFERROR('HISTORICAL FS'!G33,0) -> 0.065978324 | G14: =IFERROR('HISTORICAL FS'!H33,0) -> 0.10139826 | H14: =IFERROR('HISTORICAL FS'!I33,0) -> 0.077143622 | I14: =IFERROR('HISTORICAL FS'!J33,0) -> 0.048497453 | ... K14: =IFERROR('HISTORICAL FS'!L33,0) -> 0.06486019 | M14: =IFERROR(AVERAGE(B14:K14),0) -> 0.056593829 | N14: =IFERROR(AVERAGE(C14:L14),0) -> 0.061603538
A16: Sales expenses % Sales | B16: =IFERROR('HISTORICAL FS'!C15,0) -> 0.098680357 | C16: =IFERROR('HISTORICAL FS'!D15,0) -> 0.10796969 | D16: =IFERROR('HISTORICAL FS'!E15,0) -> 0.085483482 | E16: =IFERROR('HISTORICAL FS'!F15,0) -> 0.081266109 | F16: =IFERROR('HISTORICAL FS'!G15,0) -> 0.092151757 | G16: =IFERROR('HISTORICAL FS'!H15,0) -> 0.063474956 | H16: =IFERROR('HISTORICAL FS'!I15,0) -> 0.070808016 | I16: =IFERROR('HISTORICAL FS'!J15,0) -> 0.069577835 | ... K16: =IFERROR('HISTORICAL FS'!L15,0) -> 0.059733226 | M16: =IFERROR(AVERAGE(B16:K16),0) -> 0.079100848 | N16: =IFERROR(AVERAGE(C16:L16),0) -> 0.076925347
A17: Deprication% Sales | B17: =IFERROR('HISTORICAL FS'!C24,0) -> 0.016937695 | C17: =IFERROR('HISTORICAL FS'!D24,0) -> 0.015299144 | D17: =IFERROR('HISTORICAL FS'!E24,0) -> 0.014472243 | E17: =IFERROR('HISTORICAL FS'!F24,0) -> 0.013926816 | F17: =IFERROR('HISTORICAL FS'!G24,0) -> 0.018454103 | G17: =IFERROR('HISTORICAL FS'!H24,0) -> 0.016862406 | H17: =IFERROR('HISTORICAL FS'!I24,0) -> 0.018133509 | I17: =IFERROR('HISTORICAL FS'!J24,0) -> 0.017803478 | ... K17: =IFERROR('HISTORICAL FS'!L24,0) -> 0.023784933 | M17: =IFERROR(AVERAGE(B17:K17),0) -> 0.017852922 | N17: =IFERROR(AVERAGE(C17:L17),0) -> 0.017954614
A18: Opearting income sales% | B18: =IFERROR(B12,0) -> 0.029959295 | C18: =IFERROR(C12,0) -> 0.04929885 | D18: =IFERROR(D12,0) -> 0.09489973 | E18: =IFERROR(E12,0) -> 0.10146247 | F18: =IFERROR(F12,0) -> 0.095368574 | G18: =IFERROR(G12,0) -> 0.1436669 | H18: =IFERROR(H12,0) -> 0.11451875 | I18: =IFERROR(I12,0) -> 0.073555914 | ... K18: =IFERROR(K12,0) -> 0.089862435 | M18: =IFERROR(AVERAGE(B18:K18),0) -> 0.088503967 | N18: =IFERROR(AVERAGE(C18:L18),0) -> 0.09500893
A20: Return on capital employed | B20: =IFERROR(('HISTORICAL FS'!C17-'HISTORICAL FS'!C23)/(SUM('HISTORICAL FS'!C46,'HISTORICAL FS'!C47,'HISTORICAL FS'!C48)),0) -> 0.056044914 | C20: =IFERROR(('HISTORICAL FS'!D17-'HISTORICAL FS'!D23)/(SUM('HISTORICAL FS'!D46,'HISTORICAL FS'!D47,'HISTORICAL FS'!D48)),0) -> 0.10833563 | D20: =IFERROR(('HISTORICAL FS'!E17-'HISTORICAL FS'!E23)/(SUM('HISTORICAL FS'!E46,'HISTORICAL FS'!E47,'HISTORICAL FS'!E48)),0) -> 0.21186287 | E20: =IFERROR(('HISTORICAL FS'!F17-'HISTORICAL FS'!F23)/(SUM('HISTORICAL FS'!F46,'HISTORICAL FS'!F47,'HISTORICAL FS'!F48)),0) -> 0.21505187 | F20: =IFERROR(('HISTORICAL FS'!G17-'HISTORICAL FS'!G23)/(SUM('HISTORICAL FS'!G46,'HISTORICAL FS'!G47,'HISTORICAL FS'!G48)),0) -> 0.17506722 | G20: =IFERROR(('HISTORICAL FS'!H17-'HISTORICAL FS'!H23)/(SUM('HISTORICAL FS'!H46,'HISTORICAL FS'!H47,'HISTORICAL FS'!H48)),0) -> 0.19811117 | H20: =IFERROR(('HISTORICAL FS'!I17-'HISTORICAL FS'!I23)/(SUM('HISTORICAL FS'!I46,'HISTORICAL FS'!I47,'HISTORICAL FS'!I48)),0) -> 0.10899325 | I20: =IFERROR(('HISTORICAL FS'!J17-'HISTORICAL FS'!J23)/(SUM('HISTORICAL FS'!J46,'HISTORICAL FS'!J47,'HISTORICAL FS'!J48)),0) -> 0.075203693 | ... K20: =IFERROR(('HISTORICAL FS'!L17-'HISTORICAL FS'!L23)/(SUM('HISTORICAL FS'!L46,'HISTORICAL FS'!L47,'HISTORICAL FS'!L48)),0) -> 0.087905057 | M20: =IFERROR(AVERAGE(B20:K20),0) -> 0.13287087 | N20: =IFERROR(AVERAGE(C20:L20),0) -> 0.14140709
A21: Retained earnings % | B21: =IFERROR('HISTORICAL FS'!C43,0) -> 0.62750063 | C21: =IFERROR('HISTORICAL FS'!D43,0) -> 0.80621707 | D21: =IFERROR('HISTORICAL FS'!E43,0) -> 0.91490543 | E21: =IFERROR('HISTORICAL FS'!F43,0) -> 0.91909377 | F21: =IFERROR('HISTORICAL FS'!G43,0) -> 0.92007096 | G21: =IFERROR('HISTORICAL FS'!H43,0) -> 0.85782777 | H21: =IFERROR('HISTORICAL FS'!I43,0) -> 0.83560278 | I21: =IFERROR('HISTORICAL FS'!J43,0) -> 0.77405387 | ... K21: =IFERROR('HISTORICAL FS'!L43,0) -> 0.52852112 | M21: =IFERROR(AVERAGE(B21:K21),0) -> 0.78229771 | N21: =IFERROR(AVERAGE(C21:L21),0) -> 0.79949738
A22: Return on equity % | B22: =IFERROR('HISTORICAL FS'!C32/ SUM('HISTORICAL FS'!C46,'HISTORICAL FS'!C47),0) -> 0.026928427 | C22: =IFERROR('HISTORICAL FS'!D32/ SUM('HISTORICAL FS'!D46,'HISTORICAL FS'!D47),0) -> 0.058546637 | D22: =IFERROR('HISTORICAL FS'!E32/ SUM('HISTORICAL FS'!E46,'HISTORICAL FS'!E47),0) -> 0.13008207 | E22: =IFERROR('HISTORICAL FS'!F32/ SUM('HISTORICAL FS'!F46,'HISTORICAL FS'!F47),0) -> 0.14165379 | F22: =IFERROR('HISTORICAL FS'!G32/ SUM('HISTORICAL FS'!G46,'HISTORICAL FS'!G47),0) -> 0.12296786 | G22: =IFERROR('HISTORICAL FS'!H32/ SUM('HISTORICAL FS'!H46,'HISTORICAL FS'!H47),0) -> 0.14151047 | H22: =IFERROR('HISTORICAL FS'!I32/ SUM('HISTORICAL FS'!I46,'HISTORICAL FS'!I47),0) -> 0.073923341 | I22: =IFERROR('HISTORICAL FS'!J32/ SUM('HISTORICAL FS'!J46,'HISTORICAL FS'!J47),0) -> 0.049930925 | ... K22: =IFERROR('HISTORICAL FS'!L32/ SUM('HISTORICAL FS'!L46,'HISTORICAL FS'!L47),0) -> 0.064091137 | M22: =IFERROR(AVERAGE(B22:K22),0) -> 0.086835004 | N22: =IFERROR(AVERAGE(C22:L22),0) -> 0.093491291
A23: Self sustained growth rate | B23: =IFERROR(B21*B22,0) -> 0.016897605 | C23: =IFERROR(C21*C22,0) -> 0.047201298 | D23: =IFERROR(D21*D22,0) -> 0.11901279 | E23: =IFERROR(E21*E22,0) -> 0.13019312 | F23: =IFERROR(F21*F22,0) -> 0.11313915 | G23: =IFERROR(G21*G22,0) -> 0.12139161 | H23: =IFERROR(H21*H22,0) -> 0.06177055 | I23: =IFERROR(I21*I22,0) -> 0.038649225 | ... K23: =IFERROR(K21*K22,0) -> 0.033873519 | M23: =IFERROR(AVERAGE(B23:K23),0) -> 0.071965879 | N23: =IFERROR(AVERAGE(C23:L23),0) -> 0.078084576
A24: Interest coverage ratio | B24: =IFERROR(('HISTORICAL FS'!C17-'HISTORICAL FS'!C23)/'HISTORICAL FS'!C20,0) -> 2.0137094 | C24: =IFERROR(('HISTORICAL FS'!D17-'HISTORICAL FS'!D23)/'HISTORICAL FS'!D20,0) -> 6.3446135 | D24: =IFERROR(('HISTORICAL FS'!E17-'HISTORICAL FS'!E23)/'HISTORICAL FS'!E20,0) -> 16.281112 | E24: =IFERROR(('HISTORICAL FS'!F17-'HISTORICAL FS'!F23)/'HISTORICAL FS'!F20,0) -> 32.515865 | F24: =IFERROR(('HISTORICAL FS'!G17-'HISTORICAL FS'!G23)/'HISTORICAL FS'!G20,0) -> 32.159025 | G24: =IFERROR(('HISTORICAL FS'!H17-'HISTORICAL FS'!H23)/'HISTORICAL FS'!H20,0) -> 75.542729 | H24: =IFERROR(('HISTORICAL FS'!I17-'HISTORICAL FS'!I23)/'HISTORICAL FS'!I20,0) -> 55.711423 | I24: =IFERROR(('HISTORICAL FS'!J17-'HISTORICAL FS'!J23)/'HISTORICAL FS'!J20,0) -> 46.720422 | ... K24: =IFERROR(('HISTORICAL FS'!L17-'HISTORICAL FS'!L23)/'HISTORICAL FS'!L20,0) -> 31.557765 | M24: =IFERROR(AVERAGE(B24:K24),0) -> 32.060158 | N24: =IFERROR(AVERAGE(C24:L24),0) -> 35.398653
A26: TURNOVER RATIO
A27: Debtor Turnover ratio | B27: =IFERROR('HISTORICAL FS'!C5/'HISTORICAL FS'!C58,0) -> 9.1527055 | C27: =IFERROR('HISTORICAL FS'!D5/'HISTORICAL FS'!D58,0) -> 9.0816738 | D27: =IFERROR('HISTORICAL FS'!E5/'HISTORICAL FS'!E58,0) -> 8.5461824 | E27: =IFERROR('HISTORICAL FS'!F5/'HISTORICAL FS'!F58,0) -> 6.7257612 | F27: =IFERROR('HISTORICAL FS'!G5/'HISTORICAL FS'!G58,0) -> 7.9387998 | G27: =IFERROR('HISTORICAL FS'!H5/'HISTORICAL FS'!H58,0) -> 10.667022 | H27: =IFERROR('HISTORICAL FS'!I5/'HISTORICAL FS'!I58,0) -> 9.1880725 | I27: =IFERROR('HISTORICAL FS'!J5/'HISTORICAL FS'!J58,0) -> 7.1450769 | ... K27: =IFERROR('HISTORICAL FS'!L5/'HISTORICAL FS'!L58,0) -> 7.6915245 | M27: =IFERROR(AVERAGE(B27:K27),0) -> 8.300251 | N27: =IFERROR(AVERAGE(C27:L27),0) -> 8.2055338
A28: Credot turnover ratio | B28: =IFERROR('HISTORICAL FS'!C5/'HISTORICAL FS'!C49,0) -> 3.0275675 | C28: =IFERROR('HISTORICAL FS'!D5/'HISTORICAL FS'!D49,0) -> 3.1574806 | D28: =IFERROR('HISTORICAL FS'!E5/'HISTORICAL FS'!E49,0) -> 2.9650941 | E28: =IFERROR('HISTORICAL FS'!F5/'HISTORICAL FS'!F49,0) -> 3.5731518 | F28: =IFERROR('HISTORICAL FS'!G5/'HISTORICAL FS'!G49,0) -> 3.1424747 | G28: =IFERROR('HISTORICAL FS'!H5/'HISTORICAL FS'!H49,0) -> 3.9155423 | H28: =IFERROR('HISTORICAL FS'!I5/'HISTORICAL FS'!I49,0) -> 5.002198 | I28: =IFERROR('HISTORICAL FS'!J5/'HISTORICAL FS'!J49,0) -> 4.5787941 | ... K28: =IFERROR('HISTORICAL FS'!L5/'HISTORICAL FS'!L49,0) -> 3.9058379 | M28: =IFERROR(AVERAGE(B28:K28),0) -> 3.7092604 | N28: =IFERROR(AVERAGE(C28:L28),0) -> 3.785004
A29: Inventory turnover | B29: =IFERROR('HISTORICAL FS'!C5/'HISTORICAL FS'!C59,0) -> 7.5137709 | C29: =IFERROR('HISTORICAL FS'!D5/'HISTORICAL FS'!D59,0) -> 9.2057073 | D29: =IFERROR('HISTORICAL FS'!E5/'HISTORICAL FS'!E59,0) -> 8.9430294 | E29: =IFERROR('HISTORICAL FS'!F5/'HISTORICAL FS'!F59,0) -> 7.3033286 | F29: =IFERROR('HISTORICAL FS'!G5/'HISTORICAL FS'!G59,0) -> 6.5772618 | G29: =IFERROR('HISTORICAL FS'!H5/'HISTORICAL FS'!H59,0) -> 9.7672106 | H29: =IFERROR('HISTORICAL FS'!I5/'HISTORICAL FS'!I59,0) -> 8.6026389 | I29: =IFERROR('HISTORICAL FS'!J5/'HISTORICAL FS'!J59,0) -> 6.9219253 | ... K29: =IFERROR('HISTORICAL FS'!L5/'HISTORICAL FS'!L59,0) -> 7.3223397 | M29: =IFERROR(AVERAGE(B29:K29),0) -> 7.7869728 | N29: =IFERROR(AVERAGE(C29:L29),0) -> 7.8173285
A30: Fixed asset turnover | B30: =IFERROR('HISTORICAL FS'!C5/'HISTORICAL FS'!C52,0) -> 2.229984 | C30: =IFERROR('HISTORICAL FS'!D5/'HISTORICAL FS'!D52,0) -> 2.621735 | D30: =IFERROR('HISTORICAL FS'!E5/'HISTORICAL FS'!E52,0) -> 3.1863837 | E30: =IFERROR('HISTORICAL FS'!F5/'HISTORICAL FS'!F52,0) -> 3.8015456 | F30: =IFERROR('HISTORICAL FS'!G5/'HISTORICAL FS'!G52,0) -> 3.4128618 | G30: =IFERROR('HISTORICAL FS'!H5/'HISTORICAL FS'!H52,0) -> 3.905079 | H30: =IFERROR('HISTORICAL FS'!I5/'HISTORICAL FS'!I52,0) -> 3.9557046 | I30: =IFERROR('HISTORICAL FS'!J5/'HISTORICAL FS'!J52,0) -> 4.4569125 | ... K30: =IFERROR('HISTORICAL FS'!L5/'HISTORICAL FS'!L52,0) -> 4.9892752 | M30: =IFERROR(AVERAGE(B30:K30),0) -> 3.7087113 | N30: =IFERROR(AVERAGE(C30:L30),0) -> 3.8730143
A31: Capital turnover | B31: =IFERROR('HISTORICAL FS'!C5/SUM('HISTORICAL FS'!C46,'HISTORICAL FS'!C47),0) -> 2.340291 | C31: =IFERROR('HISTORICAL FS'!D5/SUM('HISTORICAL FS'!D46,'HISTORICAL FS'!D47),0) -> 2.5573776 | D31: =IFERROR('HISTORICAL FS'!E5/SUM('HISTORICAL FS'!E46,'HISTORICAL FS'!E47),0) -> 2.2839821 | E31: =IFERROR('HISTORICAL FS'!F5/SUM('HISTORICAL FS'!F46,'HISTORICAL FS'!F47),0) -> 2.3422642 | F31: =IFERROR('HISTORICAL FS'!G5/SUM('HISTORICAL FS'!G46,'HISTORICAL FS'!G47),0) -> 1.8637615 | G31: =IFERROR('HISTORICAL FS'!H5/SUM('HISTORICAL FS'!H46,'HISTORICAL FS'!H47),0) -> 1.3955906 | H31: =IFERROR('HISTORICAL FS'!I5/SUM('HISTORICAL FS'!I46,'HISTORICAL FS'!I47),0) -> 0.95825603 | I31: =IFERROR('HISTORICAL FS'!J5/SUM('HISTORICAL FS'!J46,'HISTORICAL FS'!J47),0) -> 1.0295577 | ... K31: =IFERROR('HISTORICAL FS'!L5/SUM('HISTORICAL FS'!L46,'HISTORICAL FS'!L47),0) -> 0.98814292 | M31: =IFERROR(AVERAGE(B31:K31),0) -> 1.6803435 | N31: =IFERROR(AVERAGE(C31:L31),0) -> 1.607016
A33: Debtor days | B33: =IFERROR(365/B27,0) -> 39.878919 | C33: =IFERROR(365/C27,0) -> 40.190829 | D33: =IFERROR(365/D27,0) -> 42.709128 | E33: =IFERROR(365/E27,0) -> 54.26895 | F33: =IFERROR(365/F27,0) -> 45.976723 | G33: =IFERROR(365/G27,0) -> 34.217612 | H33: =IFERROR(365/H27,0) -> 39.725416 | I33: =IFERROR(365/I27,0) -> 51.084125 | ... K33: =IFERROR(365/K27,0) -> 47.454832 | M33: =IFERROR(AVERAGE(B33:K33),0) -> 44.866942 | N33: =IFERROR(AVERAGE(C33:L33),0) -> 45.421167
A34: Payable days | B34: =IFERROR(365/B28,0) -> 120.55883 | C34: =IFERROR(365/C28,0) -> 115.59849 | D34: =IFERROR(365/D28,0) -> 123.09896 | E34: =IFERROR(365/E28,0) -> 102.15071 | F34: =IFERROR(365/F28,0) -> 116.1505 | G34: =IFERROR(365/G28,0) -> 93.218249 | H34: =IFERROR(365/H28,0) -> 72.967924 | I34: =IFERROR(365/I28,0) -> 79.715312 | ... K34: =IFERROR(365/K28,0) -> 93.44986 | M34: =IFERROR(AVERAGE(B34:K34),0) -> 101.23471 | N34: =IFERROR(AVERAGE(C34:L34),0) -> 99.087583
A35: Inventory days | B35: =IFERROR(365/B29,0) -> 48.577473 | C35: =IFERROR(365/C29,0) -> 39.649316 | D35: =IFERROR(365/D29,0) -> 40.813911 | E35: =IFERROR(365/E29,0) -> 49.977212 | F35: =IFERROR(365/F29,0) -> 55.494218 | G35: =IFERROR(365/G29,0) -> 37.369932 | H35: =IFERROR(365/H29,0) -> 42.428841 | I35: =IFERROR(365/I29,0) -> 52.730994 | ... K35: =IFERROR(365/K29,0) -> 49.847455 | M35: =IFERROR(AVERAGE(B35:K35),0) -> 48.078415 | N35: =IFERROR(AVERAGE(C35:L35),0) -> 48.022964
A36: Cash conversion cycle | B36: =IFERROR(B33+B35-B34,0) -> -32.102439 | C36: =IFERROR(C33+C35-C34,0) -> -35.758347 | D36: =IFERROR(D33+D35-D34,0) -> -39.575923 | E36: =IFERROR(E33+E35-E34,0) -> 2.09545 | F36: =IFERROR(F33+F35-F34,0) -> -14.679557 | G36: =IFERROR(G33+G35-G34,0) -> -21.630705 | H36: =IFERROR(H33+H35-H34,0) -> 9.1863333 | I36: =IFERROR(I33+I35-I34,0) -> 24.099807 | ... K36: =IFERROR(K33+K35-K34,0) -> 3.852427 | M36: =IFERROR(AVERAGE(B36:K36),0) -> -8.2893507 | N36: =IFERROR(AVERAGE(C36:L36),0) -> -5.643452
A38: CFO/Sales | B38: =IFERROR('HISTORICAL FS'!C76/'HISTORICAL FS'!C5,0) -> 0.072844035 | C38: =IFERROR('HISTORICAL FS'!D76/'HISTORICAL FS'!D5,0) -> 0.092875597 | D38: =IFERROR('HISTORICAL FS'!E76/'HISTORICAL FS'!E5,0) -> 0.11266292 | E38: =IFERROR('HISTORICAL FS'!F76/'HISTORICAL FS'!F5,0) -> -0.12392167 | F38: =IFERROR('HISTORICAL FS'!G76/'HISTORICAL FS'!G5,0) -> 0.22960057 | G38: =IFERROR('HISTORICAL FS'!H76/'HISTORICAL FS'!H5,0) -> 0.23280613 | H38: =IFERROR('HISTORICAL FS'!I76/'HISTORICAL FS'!I5,0) -> -0.047647491 | I38: =IFERROR('HISTORICAL FS'!J76/'HISTORICAL FS'!J5,0) -> 0.0036779144 | ... K38: =IFERROR('HISTORICAL FS'!L76/'HISTORICAL FS'!L5,0) -> 0.16751465 | M38: =IFERROR(AVERAGE(B38:K38),0) -> 0.081181507 | N38: =IFERROR(AVERAGE(C38:L38),0) -> 0.082107893
A39: CFO/Total assets | B39: =IFERROR('HISTORICAL FS'!C76/'HISTORICAL FS'!C63,0) -> 0.084226698 | C39: =IFERROR('HISTORICAL FS'!D76/'HISTORICAL FS'!D63,0) -> 0.12034183 | D39: =IFERROR('HISTORICAL FS'!E76/'HISTORICAL FS'!E63,0) -> 0.14348539 | E39: =IFERROR('HISTORICAL FS'!F76/'HISTORICAL FS'!F63,0) -> -0.1648619 | F39: =IFERROR('HISTORICAL FS'!G76/'HISTORICAL FS'!G63,0) -> 0.26605717 | G39: =IFERROR('HISTORICAL FS'!H76/'HISTORICAL FS'!H63,0) -> 0.2374178 | H39: =IFERROR('HISTORICAL FS'!I76/'HISTORICAL FS'!I63,0) -> -0.038099463 | I39: =IFERROR('HISTORICAL FS'!J76/'HISTORICAL FS'!J63,0) -> 0.003073927 | ... K39: =IFERROR('HISTORICAL FS'!L76/'HISTORICAL FS'!L63,0) -> 0.13104548 | M39: =IFERROR(AVERAGE(B39:K39),0) -> 0.083913691 | N39: =IFERROR(AVERAGE(C39:L39),0) -> 0.083878913
A40: CFO/Total debt | B40: =IFERROR('HISTORICAL FS'!C76/'HISTORICAL FS'!C48,0) -> 0.67912637 | C40: =IFERROR('HISTORICAL FS'!D76/'HISTORICAL FS'!D48,0) -> 1.4504766 | D40: =IFERROR('HISTORICAL FS'!E76/'HISTORICAL FS'!E48,0) -> 11.156782 | E40: =IFERROR('HISTORICAL FS'!F76/'HISTORICAL FS'!F48,0) -> -2.761959 | F40: =IFERROR('HISTORICAL FS'!G76/'HISTORICAL FS'!G48,0) -> 27.984057 | G40: =IFERROR('HISTORICAL FS'!H76/'HISTORICAL FS'!H48,0) -> 26.942749 | H40: =IFERROR('HISTORICAL FS'!I76/'HISTORICAL FS'!I48,0) -> -6.6794995 | I40: =IFERROR('HISTORICAL FS'!J76/'HISTORICAL FS'!J48,0) -> 0.54101222 | ... K40: =IFERROR('HISTORICAL FS'!L76/'HISTORICAL FS'!L48,0) -> 16.314889 | M40: =IFERROR(AVERAGE(B40:K40),0) -> 7.7188531 | N40: =IFERROR(AVERAGE(C40:L40),0) -> 8.5010449
A42: RETURN ON ASSETS
A43: PAT vs TOTAL ASSETS | B43: =IFERROR('HISTORICAL FS'!C32/'HISTORICAL FS'!C63,0) -> 0.013304449 | C43: =IFERROR('HISTORICAL FS'!D32/'HISTORICAL FS'!D63,0) -> 0.02966348 | D43: =IFERROR('HISTORICAL FS'!E32/'HISTORICAL FS'!E63,0) -> 0.072535638 | E43: =IFERROR('HISTORICAL FS'!F32/'HISTORICAL FS'!F63,0) -> 0.080457279 | F43: =IFERROR('HISTORICAL FS'!G32/'HISTORICAL FS'!G63,0) -> 0.076454539 | G43: =IFERROR('HISTORICAL FS'!H32/'HISTORICAL FS'!H63,0) -> 0.10340687 | H43: =IFERROR('HISTORICAL FS'!I32/'HISTORICAL FS'!I63,0) -> 0.061684897 | I43: =IFERROR('HISTORICAL FS'!J32/'HISTORICAL FS'!J63,0) -> 0.040533197 | ... K43: =IFERROR('HISTORICAL FS'!L32/'HISTORICAL FS'!L63,0) -> 0.050739651 | M43: =IFERROR(AVERAGE(B43:K43),0) -> 0.057323435 | N43: =IFERROR(AVERAGE(C43:L43),0) -> 0.062214434
A44: EBIT vs TOTAL ASSETS | B44: =IFERROR(('HISTORICAL FS'!C17-'HISTORICAL FS'!C23)/'HISTORICAL FS'!C63,0) -> 0.034640756 | C44: =IFERROR(('HISTORICAL FS'!D17-'HISTORICAL FS'!D23)/'HISTORICAL FS'!D63,0) -> 0.06387807 | D44: =IFERROR(('HISTORICAL FS'!E17-'HISTORICAL FS'!E23)/'HISTORICAL FS'!E63,0) -> 0.12086252 | E44: =IFERROR(('HISTORICAL FS'!F17-'HISTORICAL FS'!F23)/'HISTORICAL FS'!F63,0) -> 0.1349828 | F44: =IFERROR(('HISTORICAL FS'!G17-'HISTORICAL FS'!G23)/'HISTORICAL FS'!G63,0) -> 0.11051145 | G44: =IFERROR(('HISTORICAL FS'!H17-'HISTORICAL FS'!H23)/'HISTORICAL FS'!H63,0) -> 0.14651281 | H44: =IFERROR(('HISTORICAL FS'!I17-'HISTORICAL FS'!I23)/'HISTORICAL FS'!I63,0) -> 0.091570466 | I44: =IFERROR(('HISTORICAL FS'!J17-'HISTORICAL FS'!J23)/'HISTORICAL FS'!J63,0) -> 0.061476556 | ... K44: =IFERROR(('HISTORICAL FS'!L17-'HISTORICAL FS'!L23)/'HISTORICAL FS'!L63,0) -> 0.070298724 | M44: =IFERROR(AVERAGE(B44:K44),0) -> 0.090782155 | N44: =IFERROR(AVERAGE(C44:L44),0) -> 0.097020088
A45: PAT AFTER TAX BENEFIT vs TOTAL ASSET | B45: =IFERROR((('HISTORICAL FS'!C17-'HISTORICAL FS'!C23)-('HISTORICAL FS'!C20-('HISTORICAL FS'!C20*'HISTORICAL FS'!C30)))/'HISTORICAL FS'!C63,0) -> 0.021516236 | C45: =IFERROR((('HISTORICAL FS'!D17-'HISTORICAL FS'!D23)-('HISTORICAL FS'!D20-('HISTORICAL FS'!D20*'HISTORICAL FS'!D30)))/'HISTORICAL FS'!D63,0) -> 0.058327906 | D45: =IFERROR((('HISTORICAL FS'!E17-'HISTORICAL FS'!E23)-('HISTORICAL FS'!E20-('HISTORICAL FS'!E20*'HISTORICAL FS'!E30)))/'HISTORICAL FS'!E63,0) -> 0.11611577 | E45: =IFERROR((('HISTORICAL FS'!F17-'HISTORICAL FS'!F23)-('HISTORICAL FS'!F20-('HISTORICAL FS'!F20*'HISTORICAL FS'!F30)))/'HISTORICAL FS'!F63,0) -> 0.13242989 | F45: =IFERROR((('HISTORICAL FS'!G17-'HISTORICAL FS'!G23)-('HISTORICAL FS'!G20-('HISTORICAL FS'!G20*'HISTORICAL FS'!G30)))/'HISTORICAL FS'!G63,0) -> 0.10805776 | G45: =IFERROR((('HISTORICAL FS'!H17-'HISTORICAL FS'!H23)-('HISTORICAL FS'!H20-('HISTORICAL FS'!H20*'HISTORICAL FS'!H30)))/'HISTORICAL FS'!H63,0) -> 0.14512559 | H45: =IFERROR((('HISTORICAL FS'!I17-'HISTORICAL FS'!I23)-('HISTORICAL FS'!I20-('HISTORICAL FS'!I20*'HISTORICAL FS'!I30)))/'HISTORICAL FS'!I63,0) -> 0.090443007 | I45: =IFERROR((('HISTORICAL FS'!J17-'HISTORICAL FS'!J23)-('HISTORICAL FS'!J20-('HISTORICAL FS'!J20*'HISTORICAL FS'!J30)))/'HISTORICAL FS'!J63,0) -> 0.060590011 | ... K45: =IFERROR((('HISTORICAL FS'!L17-'HISTORICAL FS'!L23)-('HISTORICAL FS'!L20-('HISTORICAL FS'!L20*'HISTORICAL FS'!L30)))/'HISTORICAL FS'!L63,0) -> 0.068638274 | M45: =IFERROR(AVERAGE(B45:K45),0) -> 0.087218997 | N45: =IFERROR(AVERAGE(C45:L45),0) -> 0.094519304
A47: RETURN ON EQUITY
A48: EPS | B48: =IFERROR('HISTORICAL FS'!C37,0) -> 3.221044 | C48: =IFERROR('HISTORICAL FS'!D37,0) -> 7.7406199 | D48: =IFERROR('HISTORICAL FS'!E37,0) -> 23.503263 | E48: =IFERROR('HISTORICAL FS'!F37,0) -> 30.889886 | F48: =IFERROR('HISTORICAL FS'!G37,0) -> 31.267537 | G48: =IFERROR('HISTORICAL FS'!H37,0) -> 52.763353 | H48: =IFERROR('HISTORICAL FS'!I37,0) -> 42.593632 | I48: =IFERROR('HISTORICAL FS'!J37,0) -> 30.990902 | ... K48: =IFERROR('HISTORICAL FS'!L37,0) -> 59.376229 | M48: =IFERROR(AVERAGE(B48:K48),0) -> 33.223334 | N48: =IFERROR(AVERAGE(C48:L48),0) -> 36.556922
A49: Cash flow earning per share | B49: =IFERROR(('HISTORICAL FS'!C32+'HISTORICAL FS'!C23)/'HISTORICAL FS'!C35,0) -> 7.9624796 | C49: =IFERROR(('HISTORICAL FS'!D32+'HISTORICAL FS'!D23)/'HISTORICAL FS'!D35,0) -> 12.91354 | D49: =IFERROR(('HISTORICAL FS'!E32+'HISTORICAL FS'!E23)/'HISTORICAL FS'!E35,0) -> 29.47553 | E49: =IFERROR(('HISTORICAL FS'!F32+'HISTORICAL FS'!F23)/'HISTORICAL FS'!F35,0) -> 38.003263 | F49: =IFERROR(('HISTORICAL FS'!G32+'HISTORICAL FS'!G23)/'HISTORICAL FS'!G35,0) -> 40.013051 | G49: =IFERROR(('HISTORICAL FS'!H32+'HISTORICAL FS'!H23)/'HISTORICAL FS'!H35,0) -> 61.537834 | H49: =IFERROR(('HISTORICAL FS'!I32+'HISTORICAL FS'!I23)/'HISTORICAL FS'!I35,0) -> 52.605762 | I49: =IFERROR(('HISTORICAL FS'!J32+'HISTORICAL FS'!J23)/'HISTORICAL FS'!J35,0) -> 42.367703 | ... K49: =IFERROR(('HISTORICAL FS'!L32+'HISTORICAL FS'!L23)/'HISTORICAL FS'!L35,0) -> 81.150134 | M49: =IFERROR(AVERAGE(B49:K49),0) -> 43.61931 | N49: =IFERROR(AVERAGE(C49:L49),0) -> 47.58118
A50: Dividend per share | B50: =IFERROR('HISTORICAL FS'!C40,0) -> 1.1998369 | C50: =IFERROR('HISTORICAL FS'!D40,0) -> 1.5 | D50: =IFERROR('HISTORICAL FS'!E40,0) -> 2 | E50: =IFERROR('HISTORICAL FS'!F40,0) -> 2.4991843 | F50: =IFERROR('HISTORICAL FS'!G40,0) -> 2.4991843 | G50: =IFERROR('HISTORICAL FS'!H40,0) -> 7.5014837 | H50: =IFERROR('HISTORICAL FS'!I40,0) -> 7.0022745 | I50: =IFERROR('HISTORICAL FS'!J40,0) -> 7.0022745 | ... K50: =IFERROR('HISTORICAL FS'!L40,0) -> 27.994638 | M50: =IFERROR(AVERAGE(B50:K50),0) -> 7.7198876 | N50: =IFERROR(AVERAGE(C50:L50),0) -> 8.4443377
A51: Dividend payout ratio | B51: =IFERROR('HISTORICAL FS'!C41,0) -> 0.37249937 | C51: =IFERROR('HISTORICAL FS'!D41,0) -> 0.19378293 | D51: =IFERROR('HISTORICAL FS'!E41,0) -> 0.085094569 | E51: =IFERROR('HISTORICAL FS'!F41,0) -> 0.080906234 | F51: =IFERROR('HISTORICAL FS'!G41,0) -> 0.079929045 | G51: =IFERROR('HISTORICAL FS'!H41,0) -> 0.14217223 | H51: =IFERROR('HISTORICAL FS'!I41,0) -> 0.16439722 | I51: =IFERROR('HISTORICAL FS'!J41,0) -> 0.22594613 | ... K51: =IFERROR('HISTORICAL FS'!L41,0) -> 0.47147888 | M51: =IFERROR(AVERAGE(B51:K51),0) -> 0.21770229 | N51: =IFERROR(AVERAGE(C51:L51),0) -> 0.20050262
A52: Dividend Yield ratio | B52: =IFERROR(B50/'Data Sheet'!B8,0) -> 0.00036292706 | C52: =IFERROR(C50/'Data Sheet'!C8,0) -> 0 | D52: =IFERROR(D50/'Data Sheet'!D8,0) -> 0 | E52: =IFERROR(E50/'Data Sheet'!E8,0) -> 0 | F52: =IFERROR(F50/'Data Sheet'!F8,0) -> 0 | G52: =IFERROR(G50/'Data Sheet'!G8,0) -> 0 | H52: =IFERROR(H50/'Data Sheet'!H8,0) -> 0 | I52: =IFERROR(I50/'Data Sheet'!I8,0) -> 0 | ... K52: =IFERROR(K50/'Data Sheet'!K8,0) -> 0

Sheet FORECASTING
B2: ='Data Sheet'!B1& " - "&'Data Sheet'!A17 -> ESCORTS KUBOTA LTD - Sales
B3: YEAR WEIGHT | C3: YEAR | D3: SALES | E3: SALES GROWTH
B4: 1 | C4: 2016A | D4: 3431.99 | E4: -
B5: 2 | C5: 2017A | D5: 4145.33 | E5: =D5/D4-1 -> 0.20785026
B6: 3 | C6: 2018A | D6: 5059.34 | E6: =D6/D5-1 -> 0.22049149
B7: 4 | C7: 2019A | D7: 6262.02 | E7: =D7/D6-1 -> 0.2377148
B8: 5 | C8: 2020A | D8: 5810.09 | E8: =D8/D7-1 -> -0.072170003
B9: 6 | C9: 2021A | D9: 7014.42 | E9: =D9/D8-1 -> 0.2072825
B10: 7 | C10: 2022A | D10: 7282.65 | E10: =D10/D9-1 -> 0.038239797
B11: 8 | C11: 2023A | D11: 8428.69 | E11: =D11/D10-1 -> 0.15736579
B12: 9 | C12: 2024A | D12: 9803.59 | E12: =D12/D11-1 -> 0.16312143
B13: 10 | C13: 2025A | D13: 10243.88 | E13: =D13/D12-1 -> 0.044911099
B14: 11 | C14: 2026E | D14: =FORECAST(B14,$D$4:$D$13,$B$4:$B$13) -> 10815.793 | E14: =D14/D13-1 -> 0.055829757
B15: 12 | C15: 2027E | D15: =FORECAST(B15,$D$4:$D$13,$B$4:$B$13) -> 11555.356 | E15: =D15/D14-1 -> 0.06837801
B16: 13 | C16: 2028E | D16: =FORECAST(B16,$D$4:$D$13,$B$4:$B$13) -> 12294.918 | E16: =D16/D15-1 -> 0.064001701
B17: 14 | C17: 2029E | D17: =FORECAST(B17,$D$4:$D$13,$B$4:$B$13) -> 13034.481 | E17: =D17/D16-1 -> 0.060151878
B18: 15 | C18: 2030E | D18: =FORECAST(B18,$D$4:$D$13,$B$4:$B$13) -> 13774.043 | E18: =D18/D17-1 -> 0.056738926

Sheet BETA
A1: Date | B1: Nifty-50 | C1: ESCO | D1: Nifty-50 Return | E1: ESCO-Return | G1: SUMMARY OUTPUT
A2: 43952 | B2: 9580.3 | C2: 901.36
A3: 43983 | B3: 10302.1 | C3: 1037.82 | D3: =(B3-B2)/B2 -> 0.075342108 | E3: =(C3-C2)/C2 -> 0.15139345 | G3: Regression Statistics
A4: 44013 | B4: 11073.45 | C4: 1131.63 | D4: =(B4-B3)/B3 -> 0.074873084 | E4: =(C4-C3)/C3 -> 0.090391397 | G4: Multiple R | H4: 0.35344824
A5: 44044 | B5: 11387.5 | C5: 1085.32 | D5: =(B5-B4)/B4 -> 0.028360628 | E5: =(C5-C4)/C4 -> -0.04092327 | G5: R Square | H5: 0.12492566
A6: 44075 | B6: 11247.55 | C6: 1315.69 | D6: =(B6-B5)/B5 -> -0.012289791 | E6: =(C6-C5)/C5 -> 0.21225998 | G6: Adjusted R Square | H6: 0.10983817
A7: 44105 | B7: 11642.4 | C7: 1198.44 | D7: =(B7-B6)/B6 -> 0.035105423 | E7: =(C7-C6)/C6 -> -0.089116737 | G7: Standard Error | H7: 0.092741091
A8: 44136 | B8: 12968.95 | C8: 1400.91 | D8: =(B8-B7)/B7 -> 0.11394128 | E8: =(C8-C7)/C7 -> 0.16894463 | G8: Observations | H8: 60
A9: 44166 | B9: 13981.75 | C9: 1257.76 | D9: =(B9-B8)/B8 -> 0.078094217 | E9: =(C9-C8)/C8 -> -0.10218358
A10: 44197 | B10: 13634.6 | C10: 1203.18 | D10: =(B10-B9)/B9 -> -0.024828795 | E10: =(C10-C9)/C9 -> -0.043394606 | G10: ANOVA
A11: 44228 | B11: 14529.15 | C11: 1308.16 | D11: =(B11-B10)/B10 -> 0.065608819 | E11: =(C11-C10)/C10 -> 0.087252115 | H11: df | I11: SS | J11: MS | K11: F | L11: Significance F
A12: 44256 | B12: 14690.7 | C12: 1285.1 | D12: =(B12-B11)/B11 -> 0.011119026 | E12: =(C12-C11)/C11 -> -0.017627813 | G12: Regression | H12: 1 | I12: 0.07121625 | J12: 0.07121625 | K12: 8.2800832 | L12: 0.0056015863
A13: 44287 | B13: 14631.1 | C13: 1116.26 | D13: =(B13-B12)/B12 -> -0.0040569884 | E13: =(C13-C12)/C12 -> -0.13138277 | G13: Residual | H13: 58 | I13: 0.49885278 | J13: 0.00860091
A14: 44317 | B14: 15582.8 | C14: 1169.35 | D14: =(B14-B13)/B13 -> 0.065046374 | E14: =(C14-C13)/C13 -> 0.047560604 | G14: Total | H14: 59 | I14: 0.57006903
A15: 44348 | B15: 15721.5 | C15: 1217.55 | D15: =(B15-B14)/B14 -> 0.0089008394 | E15: =(C15-C14)/C14 -> 0.041219481
A16: 44378 | B16: 15763.05 | C16: 1184.35 | D16: =(B16-B15)/B15 -> 0.0026428776 | E16: =(C16-C15)/C15 -> -0.027267874 | H16: Coefficients | I16: Standard Error | J16: t Stat | K16: P-value | L16: Lower 95% | M16: Upper 95% | N16: Lower 95.0% | O16: Upper 95.0%
A17: 44409 | B17: 17132.2 | C17: 1346.35 | D17: =(B17-B16)/B16 -> 0.086858191 | E17: =(C17-C16)/C16 -> 0.13678389 | G17: Intercept | H17: 0.012100659 | I17: 0.012988631 | J17: 0.93163468 | K17: 0.35538725 | L17: -0.013898911 | M17: 0.038100229 | N17: -0.013898911 | O17: 0.038100229
A18: 44440 | B18: 17618.15 | C18: 1480.1 | D18: =(B18-B17)/B17 -> 0.028364717 | E18: =(C18-C17)/C17 -> 0.099342667 | G18: X Variable 1 | H18: 0.86663737 | I18: 0.30117579 | J18: 2.8775134 | K18: 0.0056015863 | L18: 0.26376852 | M18: 1.4695062 | N18: 0.26376852 | O18: 1.4695062
A19: 44470 | B19: 17671.65 | C19: 1569.4 | D19: =(B19-B18)/B18 -> 0.0030366412 | E19: =(C19-C18)/C18 -> 0.060333761
A20: 44501 | B20: 16983.2 | C20: 1846.3 | D20: =(B20-B19)/B19 -> -0.038957879 | E20: =(C20-C19)/C19 -> 0.17643685
A21: 44531 | B21: 17354.05 | C21: 1908.7 | D21: =(B21-B20)/B20 -> 0.021836285 | E21: =(C21-C20)/C20 -> 0.033797324
A22: 44562 | B22: 17339.85 | C22: 1850.35 | D22: =(B22-B21)/B21 -> -0.0008182528 | E22: =(C22-C21)/C21 -> -0.030570545
A23: 44593 | B23: 16793.9 | C23: 1850.95 | D23: =(B23-B22)/B22 -> -0.031485278 | E23: =(C23-C22)/C22 -> 0.00032426298
A24: 44621 | B24: 17464.75 | C24: 1690.85 | D24: =(B24-B23)/B23 -> 0.039946052 | E24: =(C24-C23)/C23 -> -0.086496124
A25: 44652 | B25: 17102.55 | C25: 1634.85 | D25: =(B25-B24)/B24 -> -0.020738917 | E25: =(C25-C24)/C24 -> -0.033119437
A26: 44682 | B26: 16584.55 | C26: 1629.95 | D26: =(B26-B25)/B25 -> -0.030287881 | E26: =(C26-C25)/C25 -> -0.0029972169
A27: 44713 | B27: 15780.25 | C27: 1444.8 | D27: =(B27-B26)/B26 -> -0.048496944 | E27: =(C27-C26)/C26 -> -0.11359244
A28: 44743 | B28: 17158.25 | C28: 1733 | D28: =(B28-B27)/B27 -> 0.087324345 | E28: =(C28-C27)/C27 -> 0.19947398
A29: 44774 | B29: 17759.3 | C29: 1994.75 | D29: =(B29-B28)/B28 -> 0.035029796 | E29: =(C29-C28)/C28 -> 0.15103866
A30: 44805 | B30: 17094.35 | C30: 2127.8 | D30: =(B30-B29)/B29 -> -0.037442354 | E30: =(C30-C29)/C29 -> 0.066700088
... A62: 45778 | B62: 24750.7 | C62: 3321.7 | D62: =(B62-B61)/B61 -> 0.017115829 | E62: =(C62-C61)/C61 -> 0.01923903
C65: Raw Beta | D65: =SLOPE(E3:E62,D3:D62) -> 0.86663737
C66: Intercept/Alpha | D66: =INTERCEPT(E3:E62,D3:D62) -> 0.012100659
C67: R-Squared | D67: =RSQ(E3:E62,D3:D62) -> 0.12492566
C68: Correlation | D68: =CORREL(E3:E62,D3:D62) -> 0.35344824 | E68: =SQRT(D67) -> 0.35344824
C69: SE of Beta | D69: =STEYX(E3:E62,D3:D62)/(_xlfn.STDEV.S(D3:D62)*SQRT(COUNT(D3:D62)-1)) -> 0.30117579
C70: Variance of Nifty | D70: =_xlfn.VAR.S(D3:D62) -> 0.0016071347
C71: COV of ESCO with Nifty | D71: =_xlfn.COVARIANCE.S(E3:E62,D3:D62) -> 0.001392803
C72: Beta cross check | D72: =D71/D70 -> 0.86663737
C73: Adjusted Beta | D73: =(0.67*D65)+(0.33*1) -> 0.91064704

Sheet WACC
B2: Weighted average cost of capital
B4: All figures are in IRR unless otherwise stated
B6: Peer comps
G7: Debt/ | H7: Debt/ | I7: Levered | J7: Unlevered
B8: Name of the | C8: Country | D8: Total Debt | E8: Total Equity | F8: Tax Rate 1 | G8: Equity | H8: Capital | I8: Beta 2 | J8: Beta 3
B10: VST Tillers | C10: India | D10: 0.01 | E10: 4528 | F10: 0.2517 | G10: =D10/E10 -> 2.2084806e-06 | H10: =D10/(D10+E10) -> 2.2084757e-06 | I10: 0.45 | J10: =I10/(1+(1-F10)*G10) -> 0.44999926
B11: Mahindra & Mahindra | C11: India | D11: 4000 | E11: 359600 | F11: 0.2517 | G11: =D11/E11 -> 0.011123471 | H11: =D11/(D11+E11) -> 0.0110011 | I11: 0.29 | J11: =I11/(1+(1-F11)*G11) -> 0.28760606
B12: Action Construction Equipment | C12: India | D12: 164.37 | E12: 14280 | F12: 0.2517 | G12: =D12/E12 -> 0.011510504 | H12: =D12/(D12+E12) -> 0.01137952 | I12: 0.2 | J12: =I12/(1+(1-F12)*G12) -> 0.19829205
B13: Swaraj Engines | C13: India | D13: 0.01 | E13: 4914 | F13: 0.2517 | G13: =D13/E13 -> 2.035002e-06 | H13: =D13/(D13+E13) -> 2.0349979e-06 | I13: 0.7 | J13: =I13/(1+(1-F13)*G13) -> 0.69999893
B14: Force Motors | C14: India | D14: 500 | E14: 13200 | F14: 0.2517 | G14: =D14/E14 -> 0.037878788 | H14: =D14/(D14+E14) -> 0.03649635 | I14: 0.5 | J14: =I14/(1+(1-F14)*G14) -> 0.48621829
E16: Average | F16: =AVERAGE(F10:F14) -> 0.2517 | G16: =AVERAGE(G10:G14) -> 0.012103401 | H16: =AVERAGE(H10:H14) -> 0.011776243 | I16: =AVERAGE(I10:I14) -> 0.428 | J16: =AVERAGE(J10:J14) -> 0.42442292
E17: Median | F17: =MEDIAN(F10:F14) -> 0.2517 | G17: =MEDIAN(G10:G14) -> 0.011123471 | H17: =MEDIAN(H10:H14) -> 0.0110011 | I17: =MEDIAN(I10:I14) -> 0.45 | J17: =MEDIAN(J10:J14) -> 0.44999926
B20: Cost of Debt | G20: Cost of Equity
B22: Pre cost tax of debt | E22: 0.085 | G22: Risk free rate | K22: 0.0622
B23: Tax rate | E23: 0.2517 | G23: Equity risk premium | K23: 0.08
B24: Post tax cost of debt | E24: =E22*(1-E23) -> 0.0636055 | G24: Levered Beta 4 | K24: =K33 -> 0.45104712
G25: Cost of Equity | K25: =K22+(K23*BETA!D73) -> 0.13505176
B28: Capital structure | G28: Levered Beta
D30: Current | E30: Target | G30: Comps Median Unlevered Beta | K30: =I17 -> 0.45
B31: Total Debt | C31: 105.58 | D31: =C31/$C$33 -> 0.0028464067 | E31: 0.0031 | G31: Target Debt/Equity | K31: =E35 -> 0.0031096399
B32: Market Capitalization | C32: ='Data Sheet'!B9 -> 36986.8 | D32: =C32/$C$33 -> 0.99715359 | E32: =E33-E31 -> 0.9969 | G32: Tax Rate | K32: =E23 -> 0.2517
B33: Total Capital | C33: =C31+C32 -> 37092.38 | D33: =C33/$C$33 -> 1 | E33: 1 | G33: Levered Beta | K33: =K30*(1+(1-K32)*K31) -> 0.45104712
B35: Debt/ Equity | D35: =D31/D32 -> 0.0028545319 | E35: =E31/E32 -> 0.0031096399 | G35: Weighted Average Cost of Capital
K36: Total cost | L36: Total Weight
G37: Debt | K37: =E24 -> 0.0636055 | L37: =E31 -> 0.0031
G38: Equity | K38: =K25 -> 0.13505176 | L38: =E32 -> 0.9969
G39: Weighted Average Cost of Capital | L39: =SUMPRODUCT(K37:K38,L37:L38) -> 0.13483028

Sheet VARIANCE ANALYSIS
A1: Line Item | B1: Actual FY25 | C1: Forecasted FY25(best case) | D1: Variance ₹ Cr (vs Best) | E1: Variance % (vs Best) | F1: Forecasted FY25(Worst case) | G1: Variance ₹ Cr (vs worst) | H1: Variance % (vs Worst) | I1: F/U | J1: Reason/Commentary
A3: Sales | B3: ='Profit & Loss'!K4 -> 10243.88 | C3: ='Profit & Loss'!M4 -> 11477.734 | D3: =B3-C3 -> -1233.8542 | E3: =(B3-C3)/ABS(C3) -> -0.10749981 | F3: ='Profit & Loss'!N4 -> 10714.932 | G3: =(B3-C3)/ABS(C3) -> -0.10749981 | H3: =(B3-F3)/ABS(F3) -> -0.043962189 | I3: =IF(D3>0,"Favourable",IF(D3<0,"Unfavourable","Nil")) -> Unfavourable | J3: Actual ₹10,244 Cr vs Best Case ₹11,478 Cr — missed by ₹1,234 Cr (10.7%) due to FY25 actual growth of only 4.5% vs assumed growth rate of ~12% in Best Case projection
A4: Expenses | B4: ='Profit & Loss'!K5 -> 9079.69 | C4: ='Profit & Loss'!M5 -> 10146.23 | D4: =B4-C4 -> -1066.5402 | E4: =(B4-C4)/ABS(C4) -> -0.10511689 | F4: ='Profit & Loss'!N5 -> 9561.7925 | G4: =(B4-C4)/ABS(C4) -> -0.10511689 | H4: =(B4-F4)/ABS(F4) -> -0.05041968 | I4: =IF(D4<0,"Favourable",IF(D4>0,"Unfavourable","Nil")) -> Favourable
A5: Operating Profit | B5: ='Profit & Loss'!K6 -> 1164.19 | C5: ='Profit & Loss'!M6 -> 1331.504 | D5: =B5-C5 -> -167.31401 | E5: =(B5-C5)/ABS(C5) -> -0.12565791 | F5: ='Profit & Loss'!N6 -> 1153.1393 | G5: =(B5-C5)/ABS(C5) -> -0.12565791 | H5: =(B5-F5)/ABS(F5) -> 0.0095831145 | I5: =IF(D5>0,"Favourable",IF(D5<0,"Unfavourable","Nil")) -> Unfavourable | J5: Actual ₹1,164 Cr slightly below Best Case ₹1,331 Cr — OPM compressed to 11.4% vs assumed 11.6%
A6: Other Income | B6: ='Profit & Loss'!K7 -> 600.53 | C6: ='Profit & Loss'!M7 -> 0 | D6: =B6-C6 -> 600.53 | E6: =IFERROR((B6 - C6) / ABS(C6), "N/A-Not Forecasted") -> N/A-Not Forecasted | F6: ='Profit & Loss'!N7 -> 0 | G6: =IFERROR((B6 - C6) / ABS(C6), "N/A - Not Forecasted") -> N/A - Not Forecasted | H6: =IFERROR((B6 - F6) / ABS(F6), "N/A - Not Forecasted") -> N/A - Not Forecasted | I6: =IF(D6>0,"Favourable",IF(D6<0,"Unfavourable","Nil")) -> Favourable | J6: Actual ₹600 Cr vs Best Case ₹0 — Best Case model excluded other income conservatively; actual other income from ₹5,605 Cr investment portfolio significantly boosted reported profits
A7: Depreciation | B7: ='Profit & Loss'!K8 -> 243.65 | C7: ='Profit & Loss'!M8 -> 246.2 | D7: =B7-C7 -> -2.55 | E7: =(B7-C7)/ABS(C7) -> -0.010357433 | F7: ='Profit & Loss'!N8 -> 246.2 | G7: =(B7-C7)/ABS(C7) -> -0.010357433 | H7: =(B7-F7)/ABS(F7) -> -0.010357433 | I7: =IF(D7<0,"Favourable",IF(D7>0,"Unfavourable","Nil")) -> Favourable
A8: Interest | B8: ='Profit & Loss'!K9 -> 29.17 | C8: ='Profit & Loss'!M9 -> 29.2 | D8: =B8-C8 -> -0.03 | E8: =(B8-C8)/ABS(C8) -> -0.0010273973 | F8: ='Profit & Loss'!N9 -> 29.2 | G8: =(B8-C8)/ABS(C8) -> -0.0010273973 | H8: =(B8-F8)/ABS(F8) -> -0.0010273973 | I8: =IF(D8<0,"Favourable",IF(D8>0,"Unfavourable","Nil")) -> Favourable
A9: Profit before tax | B9: ='Profit & Loss'!K10 -> 1491.9 | C9: ='Profit & Loss'!M10 -> 1056.104 | D9: =B9-C9 -> 435.79599 | E9: =(B9-C9)/ABS(C9) -> 0.41264495 | F9: ='Profit & Loss'!N10 -> 877.73933 | G9: =(B9-C9)/ABS(C9) -> 0.41264495 | H9: =(B9-F9)/ABS(F9) -> 0.69970735 | I9: =IF(D9>0,"Favourable",IF(D9<0,"Unfavourable","Nil")) -> Favourable
A10: Tax | B10: ='Profit & Loss'!K11 -> 226.95 | C10: ='Profit & Loss'!M11 -> 0.15930056 | D10: =B10-C10 -> 226.7907 | E10: =(B10-C10)/ABS(C10) -> 1423.6654 | F10: ='Profit & Loss'!N11 -> 0.15930056 | G10: =(B10-C10)/ABS(C10) -> 1423.6654 | H10: =(B10-F10)/ABS(F10) -> 1423.6654 | I10: =IF(D10<0,"Favourable",IF(D10>0,"Unfavourable","Nil")) -> Unfavourable
A11: Net profit | B11: ='Profit & Loss'!K12 -> 1264.94 | C11: ='Profit & Loss'!M12 -> 887.86605 | D11: =B11-C11 -> 377.07395 | E11: =(B11-C11)/ABS(C11) -> 0.42469689 | F11: ='Profit & Loss'!N12 -> 737.91496 | G11: =(B11-C11)/ABS(C11) -> 0.42469689 | H11: =(B11-F11)/ABS(F11) -> 0.71420836 | I11: =IF(D11>0,"Favourable",IF(D11<0,"Unfavourable","Nil")) -> Favourable | J11: Actual ₹1,265 Cr vs Best Case ₹888 Cr — Favourable by ₹377 Cr despite lower operating profit, entirely because of ₹600 Cr Other Income not modelled in Best Case
A12: EPS | B12: ='Profit & Loss'!K13 -> 113.042 | C12: ='Profit & Loss'!M13 -> 79.360344 | D12: =B12-C12 -> 33.681658 | E12: =(B12-C12)/ABS(C12) -> 0.42441422 | F12: ='Profit & Loss'!N13 -> 65.95723 | G12: =(B12-C12)/ABS(C12) -> 0.42441422 | H12: =(B12-F12)/ABS(F12) -> 0.71386825 | I12: =IF(D12>0,"Favourable",IF(D12<0,"Unfavourable","Nil")) -> Favourable

Sheet TREND ANALYSIS
A1: ESCORTS KUBOTA LIMITED - 10 YEAR TREND ANALYSIS (FY2016-FY2025)
A2: METRIC | B2: ='Data Sheet'!B16 -> 42460 | C2: ='Data Sheet'!C16 -> 42825 | D2: ='Data Sheet'!D16 -> 43190 | E2: ='Data Sheet'!E16 -> 43555 | F2: ='Data Sheet'!F16 -> 43921 | G2: ='Data Sheet'!G16 -> 44286 | H2: ='Data Sheet'!H16 -> 44651 | I2: ='Data Sheet'!I16 -> 45016 | ... K2: ='Data Sheet'!K16 -> 45747 | L2: TREND ANALYSIS
A3: Sales Growth % | B3: ='RATIO ANALYSIS'!B4 -> - | C3: ='RATIO ANALYSIS'!C4 -> 0.20785026 | D3: ='RATIO ANALYSIS'!D4 -> 0.22049149 | E3: ='RATIO ANALYSIS'!E4 -> 0.2377148 | F3: ='RATIO ANALYSIS'!F4 -> -0.072170003 | G3: ='RATIO ANALYSIS'!G4 -> 0.2072825 | H3: ='RATIO ANALYSIS'!H4 -> 0.038239797 | I3: ='RATIO ANALYSIS'!I4 -> 0.15736579 | ... K3: ='RATIO ANALYSIS'!K4 -> 0.044911099 | L3: Volatile- Strong Long-term
A4: Net profit Growth % | B4: ='RATIO ANALYSIS'!B7 -> - | C4: ='RATIO ANALYSIS'!C7 -> 2.0363541 | D4: ='RATIO ANALYSIS'!D7 -> 0.31428076 | E4: ='RATIO ANALYSIS'!E7 -> 0.012225714 | F4: ='RATIO ANALYSIS'!F7 -> 0.85540251 | G4: ='RATIO ANALYSIS'!G7 -> -0.21010896 | H4: ='RATIO ANALYSIS'!H7 -> -0.27240526 | I4: ='RATIO ANALYSIS'!I7 -> 0.34855787 | ... K4: ='RATIO ANALYSIS'!K7 -> 0.056048885 | L4: Volatile- Strong Long-term
A5: EBITDA Margin % | B5: ='RATIO ANALYSIS'!B11 -> 0.04689699 | C5: ='RATIO ANALYSIS'!C11 -> 0.064597993 | D5: ='RATIO ANALYSIS'!D11 -> 0.10937197 | E5: ='RATIO ANALYSIS'!E11 -> 0.11538928 | F5: ='RATIO ANALYSIS'!F11 -> 0.11382268 | G5: ='RATIO ANALYSIS'!G11 -> 0.16052931 | H5: ='RATIO ANALYSIS'!H11 -> 0.13265226 | I5: ='RATIO ANALYSIS'!I11 -> 0.091359393 | ... K5: ='RATIO ANALYSIS'!K11 -> 0.11364737 | L5: Expanding
A6: Net profit margin % | B6: ='RATIO ANALYSIS'!B14 -> 0.011506444 | C6: ='RATIO ANALYSIS'!C14 -> 0.022893232 | D6: ='RATIO ANALYSIS'!D14 -> 0.056954069 | E6: ='RATIO ANALYSIS'!E14 -> 0.06047729 | F6: ='RATIO ANALYSIS'!F14 -> 0.065978324 | G6: ='RATIO ANALYSIS'!G14 -> 0.10139826 | H6: ='RATIO ANALYSIS'!H14 -> 0.077143622 | I6: ='RATIO ANALYSIS'!I14 -> 0.048497453 | ... K6: ='RATIO ANALYSIS'!K14 -> 0.06486019 | L6: Expanding
A7: ROCE % | B7: ='RATIO ANALYSIS'!B20 -> 0.056044914 | C7: ='RATIO ANALYSIS'!C20 -> 0.10833563 | D7: ='RATIO ANALYSIS'!D20 -> 0.21186287 | E7: ='RATIO ANALYSIS'!E20 -> 0.21505187 | F7: ='RATIO ANALYSIS'!F20 -> 0.17506722 | G7: ='RATIO ANALYSIS'!G20 -> 0.19811117 | H7: ='RATIO ANALYSIS'!H20 -> 0.10899325 | I7: ='RATIO ANALYSIS'!I20 -> 0.075203693 | ... K7: ='RATIO ANALYSIS'!K20 -> 0.087905057 | L7: Peaked FY19- Moderating
A8: ROE % | B8: ='RATIO ANALYSIS'!B22 -> 0.026928427 | C8: ='RATIO ANALYSIS'!C22 -> 0.058546637 | D8: ='RATIO ANALYSIS'!D22 -> 0.13008207 | E8: ='RATIO ANALYSIS'!E22 -> 0.14165379 | F8: ='RATIO ANALYSIS'!F22 -> 0.12296786 | G8: ='RATIO ANALYSIS'!G22 -> 0.14151047 | H8: ='RATIO ANALYSIS'!H22 -> 0.073923341 | I8: ='RATIO ANALYSIS'!I22 -> 0.049930925 | ... K8: ='RATIO ANALYSIS'!K22 -> 0.064091137 | L8: Peaked FY19- Moderating
A9: Interest coverage ratio % | B9: ='RATIO ANALYSIS'!B24 -> 2.0137094 | C9: ='RATIO ANALYSIS'!C24 -> 6.3446135 | D9: ='RATIO ANALYSIS'!D24 -> 16.281112 | E9: ='RATIO ANALYSIS'!E24 -> 32.515865 | F9: ='RATIO ANALYSIS'!F24 -> 32.159025 | G9: ='RATIO ANALYSIS'!G24 -> 75.542729 | H9: ='RATIO ANALYSIS'!H24 -> 55.711423 | I9: ='RATIO ANALYSIS'!I24 -> 46.720422 | ... K9: ='RATIO ANALYSIS'!K24 -> 31.557765 | L9: Improving
A10: Debtor days | B10: ='RATIO ANALYSIS'!B33 -> 39.878919 | C10: ='RATIO ANALYSIS'!C33 -> 40.190829 | D10: ='RATIO ANALYSIS'!D33 -> 42.709128 | E10: ='RATIO ANALYSIS'!E33 -> 54.26895 | F10: ='RATIO ANALYSIS'!F33 -> 45.976723 | G10: ='RATIO ANALYSIS'!G33 -> 34.217612 | H10: ='RATIO ANALYSIS'!H33 -> 39.725416 | I10: ='RATIO ANALYSIS'!I33 -> 51.084125 | ... K10: ='RATIO ANALYSIS'!K33 -> 47.454832 | L10: Gradually Rising-Watch
A11: Cash conversion cycle | B11: ='RATIO ANALYSIS'!B36 -> -32.102439 | C11: ='RATIO ANALYSIS'!C36 -> -35.758347 | D11: ='RATIO ANALYSIS'!D36 -> -39.575923 | E11: ='RATIO ANALYSIS'!E36 -> 2.09545 | F11: ='RATIO ANALYSIS'!F36 -> -14.679557 | G11: ='RATIO ANALYSIS'!G36 -> -21.630705 | H11: ='RATIO ANALYSIS'!H36 -> 9.1863333 | I11: ='RATIO ANALYSIS'!I36 -> 24.099807 | ... K11: ='RATIO ANALYSIS'!K36 -> 3.852427 | L11: Deteriorating- Turning positive
A12: CFO/Sales | B12: ='RATIO ANALYSIS'!B38 -> 0.072844035 | C12: ='RATIO ANALYSIS'!C38 -> 0.092875597 | D12: ='RATIO ANALYSIS'!D38 -> 0.11266292 | E12: ='RATIO ANALYSIS'!E38 -> -0.12392167 | F12: ='RATIO ANALYSIS'!F38 -> 0.22960057 | G12: ='RATIO ANALYSIS'!G38 -> 0.23280613 | H12: ='RATIO ANALYSIS'!H38 -> -0.047647491 | I12: ='RATIO ANALYSIS'!I38 -> 0.0036779144 | ... K12: ='RATIO ANALYSIS'!K38 -> 0.16751465 | L12: Volatile- FY19 & FY22 Weak
A13: EPS | B13: ='RATIO ANALYSIS'!B48 -> 3.221044 | C13: ='RATIO ANALYSIS'!C48 -> 7.7406199 | D13: ='RATIO ANALYSIS'!D48 -> 23.503263 | E13: ='RATIO ANALYSIS'!E48 -> 30.889886 | F13: ='RATIO ANALYSIS'!F48 -> 31.267537 | G13: ='RATIO ANALYSIS'!G48 -> 52.763353 | H13: ='RATIO ANALYSIS'!H48 -> 42.593632 | I13: ='RATIO ANALYSIS'!I48 -> 30.990902 | ... K13: ='RATIO ANALYSIS'!K48 -> 59.376229 | L13: Stringly Rising
A14: EBITDA Growth% | B14: ='RATIO ANALYSIS'!B5 -> - | C14: ='RATIO ANALYSIS'!C5 -> 1.0664351 | D14: ='RATIO ANALYSIS'!D5 -> 0.30581007 | E14: ='RATIO ANALYSIS'!E5 -> -0.084766874 | F14: ='RATIO ANALYSIS'!F5 -> 0.70268554 | G14: ='RATIO ANALYSIS'!G5 -> -0.14205787 | H14: ='RATIO ANALYSIS'!H5 -> -0.20290665 | I14: ='RATIO ANALYSIS'!I5 -> 0.46793673 | ... K14: ='RATIO ANALYSIS'!K5 -> 0.04514727 | L14: Volatile- Strong Long-term
A17: Profitability: EBITDA margin expanded from 4.7% (FY16) to 11.4% (FY25) margins more than doubled over the decade driven by operating leverage and raw material cost discipline. Net profit margin similarly rose from 1.1% to 6.5%.
A18: Growth: Sales grew at a 10-year CAGR of ~12.9% with a single dip in FY20 (COVID + rural demand slowdown). Net profit growth was more volatile but directionally strong.
A19: Capital Efficiency: ROCE peaked at 21.5% in FY19 and has moderated to ~8.8% by FY25 as the equity base (reserves) expanded rapidly from retained profits. ROE tells the same story strong profits but a growing denominator.
A20: Leverage: Interest Coverage improved from a concerning 2x in FY16 to 31.6x in FY25 reflecting consistent debt repayment (borrowings fell from ₹368 Cr to ₹105 Cr) and strong EBIT growth.
A21: Working Capital: CCC turned from negative (-32 days in FY16) to positive (+4 days in FY25) a gradual deterioration in working capital efficiency. Debtor days rose from 40 to 53 at peak, signalling slower collections as the business scaled.
A22: Cash Quality: CFO/Sales was volatile severely negative in FY19 (-12.4%) due to large working capital build, and weak again in FY22 (-4.8%). FY25 recovery to 16.75% is strong and confirms earnings quality has improved.
A23: EPS: EPS grew from ₹3.22 to ₹59.38 an 18x increase over 10 years reflecting both profit growth and the effect of share buybacks reducing the share count.

Sheet SENSITIVITY SCENARIO ANALYSIS
A1: SCENARIO ANALYSIS - ESCORTS KUBOTA ANALYSIS
A2: SCENARIO ASSUMPTIONS | H2: tornato
A3: ASSUMPTION | B3: BEAR CASE | C3: BASE CASE | D3: BULL CASE
A4: Revenue Growth % | B4: 0.03 | C4: 0.06 | D4: 0.1
A5: EBITDA Margin % | B5: 0.095 | C5: 0.115 | D5: 0.13
A6: Other Income (₹ Cr) | B6: 500 | C6: 600 | D6: 700
A7: Depriciation (₹ Cr) | B7: 260 | C7: 260 | D7: 260
A8: Interest (₹ Cr) | B8: 25 | C8: 25 | D8: 25
A9: Tax rate % | B9: 0.2517 | C9: 0.2517 | D9: 0.2517
A10: No of Shares (Cr) | B10: 11.9 | C10: 11.9 | D10: 11.9
A13: PROJECTED INCOME STATEMENT- FY2026E
A14: LINE ITEM | B14: BEAR CASE | C14: BASE CASE | D14: BULL CASE
A15: Base Revenue (FY25 ACTUAL) | B15: ='Profit & Loss'!K4 -> 10243.88 | C15: ='Profit & Loss'!K4 -> 10243.88 | D15: ='Profit & Loss'!K4 -> 10243.88
A16: Projected Revenue (FY26E) | B16: =B15*(1+B4) -> 10551.196 | C16: =C15*(1+C4) -> 10858.513 | D16: =D15*(1+D4) -> 11268.268
A17: Projected EBITDA FY26E) | B17: =B16*B5 -> 1002.3637 | C17: =C16*C5 -> 1248.729 | D17: =D16*D5 -> 1464.8748
A18: Other Income | B18: =B6 -> 500 | C18: =C6 -> 600 | D18: =D6 -> 700
A19: Depreciation | B19: =B7 -> 260 | C19: =C7 -> 260 | D19: =D7 -> 260
A20: EBIT | B20: =B17-B19 -> 742.36366 | C20: =C17-C19 -> 988.72897 | D20: =D17-D19 -> 1204.8748
A21: Interest | B21: =B8 -> 25 | C21: =C8 -> 25 | D21: =D8 -> 25
A22: PBT | B22: =B20+B18-B21 -> 1217.3637 | C22: =C20+C18-C21 -> 1563.729 | D22: =D20+D18-D21 -> 1879.8748
A23: Tax | B23: =B22*B9 -> 306.41043 | C23: =C22*C9 -> 393.59058 | D23: =D22*D9 -> 473.1645
A24: Net Profit | B24: =B22-B23 -> 910.95323 | C24: =C22-C23 -> 1170.1384 | D24: =D22-D23 -> 1406.7103
A25: EPS | B25: =B24/B10 -> 76.550691 | C25: =C24/C10 -> 98.330957 | D25: =D24/D10 -> 118.21095
A27: SCENARIO vs ACTUAL FY25
A28: METRIC | B28: BEAR vs FY25 | C28: BASE vs FY25 | D28: BULLvs FY-25
A29: Revenue Variance ₹ | B29: =B16-B15 -> 307.3164 | C29: =C16-C15 -> 614.6328 | D29: =D16-D15 -> 1024.388
A30: Revenue Variance % | B30: =B16-B15-1 -> 306.3164 | C30: =C16-C15-1 -> 613.6328 | D30: =D16-D15-1 -> 1023.388
A31: Net Profit Variance ₹ | B31: =B24-'Profit & Loss'!K12 -> -353.98677 | C31: =C24-'Profit & Loss'!K12 -> -94.80161 | D31: =D24-'Profit & Loss'!K12 -> 141.77034
A32: Net Profit Variance % | B32: =B24-'Profit & Loss'!K12-1 -> -354.98677 | C32: =C24-'Profit & Loss'!K12-1 -> -95.80161 | D32: =D24-'Profit & Loss'!K12-1 -> 140.77034
A33: EPS Variance ₹ | B33: =B25-'Profit & Loss'!K13 -> -36.491311 | C33: =C25-'Profit & Loss'!K13 -> -14.711045 | D33: =D25-'Profit & Loss'!K13 -> 5.1689514
A36: WACC SENSITIVITY- Beta vs Equity Risk Premium
A37: =(WACC!E24*WACC!E31)+((WACC!K22+H38*H37)*WACC!E32) -> 0.13483028 | B37: 0.07 | C37: 0.075 | D37: 0.08 | E37: 0.085 | F37: 0.09 | H37: =WACC!K23 -> 0.08
A38: 0.7 | B38: 0.11105246 | C38: 0.11454161 | D38: 0.11803076 | E38: 0.12151991 | F38: 0.12500906 | H38: =BETA!D73 -> 0.91064704
A39: 0.8 | B39: 0.11803076 | C39: 0.12201836 | D39: 0.12600596 | E39: 0.12999356 | F39: 0.13398116
A40: 0.91 | B40: 0.12570689 | C40: 0.13024278 | D40: 0.13477868 | E40: 0.13931457 | F40: 0.14385047
A41: 1 | B41: 0.13198736 | C41: 0.13697186 | D41: 0.14195636 | E41: 0.14694086 | F41: 0.15192536
A42: 1.1 | B42: 0.13896566 | C42: 0.14444861 | D42: 0.14993156 | E42: 0.15541451 | F42: 0.16089746
A45: NET PROFIT SENSITIVITY -Revenue Growth % vs EBITDA Margin %
A46: =(C15 * (1 + H46) * H47 - C19 + C18 - C21) * (1 - C9) -> 1170.1384 | B46: 0.095 | C46: 0.105 | D46: 0.115 | E46: 0.125 | F46: 0.135 | H46: =C4 -> 0.06
A47: 0.02 | B47: 978.501 | C47: 1056.6891 | D47: 1134.8771 | E47: 1213.0652 | F47: 1291.2532 | H47: =C5 -> 0.115
A48: 0.04 | B48: 993.06545 | C48: 1072.7866 | D48: 1152.5078 | E48: 1232.2289 | F48: 1311.9501
A49: 0.06 | B49: 1007.6299 | C49: 1088.8841 | D49: 1170.1384 | E49: 1251.3926 | F49: 1332.6469
A50: 0.08 | B50: 1022.1943 | C50: 1104.9817 | D50: 1187.769 | E50: 1270.5564 | F50: 1353.3437
A51: 0.1 | B51: 1036.7588 | C51: 1121.0792 | D51: 1205.3997 | E51: 1289.7201 | F51: 1374.0406
A54: EPS SENSITIVITY — Revenue Growth % vs EBITDA Margin %
A55: =(C15 * (1 + H46) * H47 - C19 + C18 - C21) * (1 - C9) / C10 -> 98.330957 | B55: 0.095 | C55: 0.105 | D55: 0.115 | E55: 0.125 | F55: 0.135
A56: 0.02 | B56: 82.226975 | C56: 88.7974 | D56: 95.367824 | E56: 101.93825 | F56: 108.50867
A57: 0.04 | B57: 83.450878 | C57: 90.150134 | D57: 96.849391 | E57: 103.54865 | F57: 110.2479
A58: 0.06 | B58: 84.67478 | C58: 91.502869 | D58: 98.330957 | E58: 105.15905 | F58: 111.98713
A59: 0.08 | B59: 85.898683 | C59: 92.855603 | D59: 99.812523 | E59: 106.76944 | F59: 113.72636
A60: 0.1 | B60: 87.122586 | C60: 94.208338 | D60: 101.29409 | E60: 108.37984 | F60: 115.46559

Sheet DCF
A1: ="DCF MODEL- "& 'Data Sheet'!B1 -> DCF MODEL- ESCORTS KUBOTA LTD
A2: VALUATION DATE: May 2025
A4: ASSUMPTIONS
A5: WACC | B5: =WACC!L39 -> 0.13483028
A6: Terminal growth rate (g) | B6: 0.04
A7: EBIT Margin % | B7: ='RATIO ANALYSIS'!K18 -> 0.089862435
A8: D&A % of Sales | B8: ='RATIO ANALYSIS'!K17 -> 0.023784933
A9: Capex % of Sales | B9: =ABS(CFS!M11/'HISTORICAL FS'!L5) -> 0.024111958
A10: NWC % of Sales | B10: =('Data Sheet'!K67+'Data Sheet'!K68-('Data Sheet'!K60-'Data Sheet'!K59))/'HISTORICAL FS'!L5 -> 0.020822188
A11: Tax Rate | B11: =WACC!E23 -> 0.2517
A12: Net cash | B12: ='Data Sheet'!K69-'Data Sheet'!K59 -> 1018.95
A13: Shares outstanding | B13: ='Data Sheet'!B6 -> 11.18778
A14: Current market price | B14: ='Data Sheet'!B8 -> 3306
A15: EV/EBITDA Exit multiplier | B15: =12 -> 12
A17: PROJECTED INCOME STATEMENT
A18: LINE ITEM | B18: VALUES
A19: FY26E | B19: =FORECASTING!D14 -> 10815.793
A20: FY27E | B20: =FORECASTING!D15 -> 11555.356
A21: FY28E | B21: =FORECASTING!D16 -> 12294.918
A22: FY29E | B22: =FORECASTING!D17 -> 13034.481
A23: FY30E | B23: =FORECASTING!D18 -> 13774.043
A25: PROJECTED P&L FOR FCF
A26: LINE ITEM | B26: VALUES
A27: FY26E | B27: =B19*$B$7 -> 971.93352
A28: FY27E | B28: =B20*$B$7 -> 1038.3924
A29: FY28E | B29: =B21*$B$7 -> 1104.8513
A30: FY29E | B30: =B22*$B$7 -> 1171.3102
A31: FY30E | B31: =B23*$B$7 -> 1237.769
A33: NOPAT/ EBIT FOR FCF
A34: LINE ITEM | B34: VALUES
A35: FY26E | B35: =B27*(1-$B$11) -> 727.29786
A36: FY27E | B36: =B28*(1-$B$11) -> 777.02904
A37: FY28E | B37: =B29*(1-$B$11) -> 826.76022
A38: FY29E | B38: =B30*(1-$B$11) -> 876.4914
A39: FY30E | B39: =B31*(1-$B$11) -> 926.22258
A41: DEPRECIATION AND AMMORTIATION FOR FCF
A42: LINE ITEM | B42: VALUES
A43: FY26E | B43: =B19*$B$8 -> 257.25292
A44: FY27E | B44: =B20*$B$8 -> 274.84336
A45: FY28E | B45: =B21*$B$8 -> 292.43381
A46: FY29E | B46: =B22*$B$8 -> 310.02425
A47: FY30E | B47: =B23*$B$8 -> 327.61469
A49: CAPEX FOR FCF
A50: LINE ITEM | B50: VALUES
A51: FY26E | B51: =-(B19*B$9) -> -260.78995
A52: FY27E | B52: =-(B20*B$9) -> -278.62225
A53: FY28E | B53: =-(B21*B$9) -> -296.45455
A54: FY29E | B54: =-(B22*B$9) -> -314.28684
A55: FY30E | B55: =-(B23*B$9) -> -332.11914
A57: CHANGE IN NWC
A58: LINE ITEM | B58: VALUES | C58: CHANGE
A59: FY25A | B59: =FORECASTING!D13*DCF!B10 -> 213.3 | C59: -
A60: FY26E | B60: =B19*B$10 -> 225.20849 | C60: =-(B60-B59) -> -11.908487
A61: FY27E | B61: =B20*B$10 -> 240.6078 | C61: =-(B61-B60) -> -15.399308
A62: FY28E | B62: =B21*B$10 -> 256.0071 | C62: =-(B62-B61) -> -15.399308
A63: FY29E | B63: =B22*B$10 -> 271.40641 | C63: =-(B63-B62) -> -15.399308
A64: FY30E | B64: =B23*B$10 -> 286.80572 | C64: =-(B64-B63) -> -15.399308
A66: FREE CASH FLOWS TO FIRM (FCFF)
A67: Year | B67: Revenue | C67: NOPAT | D67: D&A | E67: Capex | F67: ΔNWC | G67: FCFF
A68: FY26E | B68: =B19 -> 10815.793 | C68: =B35 -> 727.29786 | D68: =B43 -> 257.25292 | E68: =B51 -> -260.78995 | F68: =C60 -> -11.908487 | G68: =C68+D68+(E68)+(F68) -> 711.85234
A69: FY27E | B69: =B20 -> 11555.356 | C69: =B36 -> 777.02904 | D69: =B44 -> 274.84336 | E69: =B52 -> -278.62225 | F69: =C61 -> -15.399308 | G69: =C69+D69+(E69)+(F69) -> 757.85084
A70: FY28E | B70: =B21 -> 12294.918 | C70: =B37 -> 826.76022 | D70: =B45 -> 292.43381 | E70: =B53 -> -296.45455 | F70: =C62 -> -15.399308 | G70: =C70+D70+(E70)+(F70) -> 807.34017
A71: FY29E | B71: =B22 -> 13034.481 | C71: =B38 -> 876.4914 | D71: =B46 -> 310.02425 | E71: =B54 -> -314.28684 | F71: =C63 -> -15.399308 | G71: =C71+D71+(E71)+(F71) -> 856.82949
A72: FY30E | B72: =B23 -> 13774.043 | C72: =B39 -> 926.22258 | D72: =B47 -> 327.61469 | E72: =B55 -> -332.11914 | F72: =C64 -> -15.399308 | G72: =C72+D72+(E72)+(F72) -> 906.31882
A74: DISCOUT FACTORS
A75: Year | B75: Time | C75: DF | D75: PV
A76: FY26E | B76: 1 | C76: =1/(1+$B$5)^B76 -> 0.88118904 | D76: =G68*C76 -> 627.27648
A77: FY27E | B77: 2 | C77: =1/(1+$B$5)^B77 -> 0.77649412 | D77: =G69*C77 -> 588.46672
A78: FY28E | B78: 3 | C78: =1/(1+$B$5)^B78 -> 0.6842381 | D78: =G70*C78 -> 552.4129
A79: FY29E | B79: 4 | C79: =1/(1+$B$5)^B79 -> 0.60294311 | D79: =G71*C79 -> 516.61944
A80: FY30E | B80: 5 | C80: =1/(1+$B$5)^B80 -> 0.53130686 | D80: =G72*C80 -> 481.53341
A82: TERMINAL VALUE
B83: TERMINAL VALUE | C83: PV OF TERMINAL VALUE
A84: GORDEN GROWTH MODEL | B84: =G72*(1+B6)/(B5-B6) -> 9939.5633 | C84: =B84/(1+B5)^5 -> 5280.9582
A85: EXIT MULTIPLE METHOD | B85: ='HISTORICAL FS'!L18*DCF!B23*DCF!B15 -> 18784.605 | C85: =B85/(1+B5)^5 -> 9980.3894
B87: ENTERPRISE VALUE
B88: GORDEN GROWTH MODEL | C88: EXIT MULTIPLE METHOD
A89: PV of FCFF | B89: =SUM(D76:D80) -> 2766.309 | C89: =SUM(D76:D80) -> 2766.309
A90: PV of Terminal value | B90: =C84 -> 5280.9582 | C90: =C85 -> 9980.3894
A91: Enterprise value | B91: =SUM(B89:B90) -> 8047.2671 | C91: =SUM(C89:C90) -> 12746.698
A92: Terminal value as % OF EV | B92: =B90/B91 -> 0.65624244 | C92: =C90/C91 -> 0.78297839
A94: EQUITY VALUE
A95: GORDEN GROWTH MODEL | B95: EXIT MULTIPLE METHOD
A96: =B91+B12 -> 9066.2171 | B96: =C91+B12 -> 13765.648
A98: Implied Share Price
A99: GORDEN GROWTH MODEL | B99: EXIT MULTIPLE METHOD
A100: =A96/B13 -> 810.36786 | B100: =B96/B13 -> 1230.4182
A101: =(B14-A100)/A100 -> 3.0796287 | B101: =(B14-B100)/B100 -> 1.6868912

Sheet CFS
B1: 41699 | C1: 42064 | D1: 42430 | E1: 42795 | F1: 43160 | G1: 43525 | H1: 43891 | I1: 44256 | J1: 44621 | K1: 44986 | L1: 45352 | M1: 45717
A2: Cash from Operating Activity - | B2: 347 | C2: 2 | D2: 222 | E2: 301 | F2: 472 | G2: -241 | H2: 817 | I2: 1119 | J2: 41 | K2: 236 | L2: 795 | M2: 1207
A3: Profit from operations | B3: 379 | C3: 137 | D3: 178 | E3: 305 | F3: 578 | G3: 727 | H3: 647 | I3: 1111 | J3: 936 | K3: 815 | L3: 1375 | M3: 1416
A4: Receivables | B4: 112 | C4: -69 | D4: -15 | E4: -79 | F4: -143 | G4: -324 | H4: 170 | I4: 47 | J4: -142 | K4: -384 | L4: -51 | M4: -179
A5: Inventory | B5: -59 | C5: 81 | D5: 22 | E5: -57 | F5: -123 | G5: -275 | H5: 0 | I5: 148 | J5: -129 | K5: -355 | L5: -123 | M5: 163
A6: Payables | B6: -30 | C6: -128 | D6: 42 | E6: 155 | F6: 347 | G6: -1 | H6: 87 | I6: -20 | J6: -255 | K6: 357 | L6: -98 | M6: 81
A7: Other WC items | B7: 0 | C7: 0 | D7: -13 | E7: 21 | F7: -85 | G7: -152 | H7: 86 | I7: 86 | J7: -116 | K7: -10 | L7: -65 | M7: 85
A8: Working capital changes | B8: 24 | C8: -116 | D8: 36 | E8: 40 | F8: -4 | G8: -751 | H8: 344 | I8: 261 | J8: -641 | K8: -392 | L8: -338 | M8: 150
A9: Direct taxes | B9: -56 | C9: -19 | D9: 8 | E9: -44 | F9: -102 | G9: -217 | H9: -174 | I9: -253 | J9: -254 | K9: -186 | L9: -241 | M9: -358
A10: Cash from Investing Activity - | B10: -62 | C10: 19 | D10: -25 | E10: -140 | F10: -378 | G10: -14 | H10: -429 | I10: -2197 | J10: -1871 | K10: -68 | L10: -765 | M10: -403
A11: Fixed assets purchased | B11: -118 | C11: -52 | D11: -54 | E11: -78 | F11: -115 | G11: -150 | H11: -195 | I11: -123 | J11: -186 | K11: -219 | L11: -283 | M11: -247
A12: Fixed assets sold | B12: 0 | C12: 0 | D12: 2 | E12: 13 | F12: 14 | G12: 11 | H12: 5 | I12: 9 | J12: 32 | K12: 5 | L12: 15 | M12: 9
A13: Investments purchased | B13: 0 | C13: -2 | D13: 0 | E13: -160 | F13: -298 | G13: 0 | H13: -211 | I13: -978 | J13: -2851 | K13: -423 | L13: -130 | M13: -227
... A28: Net Cash Flow | B28: 49 | C28: 10 | D28: 1 | E28: 23 | F28: 94 | G28: -63 | H28: 79 | I28: -64 | J28: -18 | K28: 99 | L28: 52 | M28: 104

Sheet Profit & Loss
A1: ='Data Sheet'!B1 -> ESCORTS KUBOTA LTD | H1: =UPDATE | M1: SCREENER.IN
A3: Narration | B3: ='Data Sheet'!B16 -> 42460 | C3: ='Data Sheet'!C16 -> 42825 | D3: ='Data Sheet'!D16 -> 43190 | E3: ='Data Sheet'!E16 -> 43555 | F3: ='Data Sheet'!F16 -> 43921 | G3: ='Data Sheet'!G16 -> 44286 | H3: ='Data Sheet'!H16 -> 44651 | I3: ='Data Sheet'!I16 -> 45016 | ... K3: ='Data Sheet'!K16 -> 45747 | L3: Trailing | M3: Best Case | N3: Worst Case
A4: Sales | B4: ='Data Sheet'!B17 -> 3431.99 | C4: ='Data Sheet'!C17 -> 4145.33 | D4: ='Data Sheet'!D17 -> 5059.34 | E4: ='Data Sheet'!E17 -> 6262.02 | F4: ='Data Sheet'!F17 -> 5810.09 | G4: ='Data Sheet'!G17 -> 7014.42 | H4: ='Data Sheet'!H17 -> 7282.65 | I4: ='Data Sheet'!I17 -> 8428.69 | ... K4: ='Data Sheet'!K17 -> 10243.88 | L4: =SUM(Quarters!H4:K4) -> 10488.54 | M4: =$K4+M23*K4 -> 11477.734 | N4: =$K4+N23*L4 -> 10714.932
A5: Expenses | B5: =SUM('Data Sheet'!B18,'Data Sheet'!B20:B24, -1*'Data Sheet'!B19) -> 3271.04 | C5: =SUM('Data Sheet'!C18,'Data Sheet'!C20:C24, -1*'Data Sheet'!C19) -> 3877.55 | D5: =SUM('Data Sheet'!D18,'Data Sheet'!D20:D24, -1*'Data Sheet'!D19) -> 4505.99 | E5: =SUM('Data Sheet'!E18,'Data Sheet'!E20:E24, -1*'Data Sheet'!E19) -> 5539.45 | F5: =SUM('Data Sheet'!F18,'Data Sheet'!F20:F24, -1*'Data Sheet'!F19) -> 5148.77 | G5: =SUM('Data Sheet'!G18,'Data Sheet'!G20:G24, -1*'Data Sheet'!G19) -> 5888.4 | H5: =SUM('Data Sheet'!H18,'Data Sheet'!H20:H24, -1*'Data Sheet'!H19) -> 6316.59 | I5: =SUM('Data Sheet'!I18,'Data Sheet'!I20:I24, -1*'Data Sheet'!I19) -> 7658.65 | ... K5: =SUM('Data Sheet'!K18,'Data Sheet'!K20:K24, -1*'Data Sheet'!K19) -> 9079.69 | L5: =SUM(Quarters!H5:K5) -> 9271.79 | M5: =M4-M6 -> 10146.23 | N5: =N4-N6 -> 9561.7925
A6: Operating Profit | B6: =B4-B5 -> 160.95 | C6: =C4-C5 -> 267.78 | D6: =D4-D5 -> 553.35 | E6: =E4-E5 -> 722.57 | F6: =F4-F5 -> 661.32 | G6: =G4-G5 -> 1126.02 | H6: =H4-H5 -> 966.06 | I6: =I4-I5 -> 770.04 | ... K6: =K4-K5 -> 1164.19 | L6: =SUM(Quarters!H6:K6) -> 1216.75 | M6: =M4*M24 -> 1331.504 | N6: =N4*N24 -> 1153.1393
A7: Other Income | B7: ='Data Sheet'!B25 -> 30.66 | C7: ='Data Sheet'!C25 -> 35.85 | D7: ='Data Sheet'!D25 -> 58.44 | E7: ='Data Sheet'!E25 -> 99.19 | F7: ='Data Sheet'!F25 -> 88.38 | G7: ='Data Sheet'!G25 -> 160.38 | H7: ='Data Sheet'!H25 -> 173.8 | I7: ='Data Sheet'!I25 -> 227.88 | ... K7: ='Data Sheet'!K25 -> 600.53 | L7: =SUM(Quarters!H7:K7) -> 563.29 | M7: 0 | N7: 0
A8: Depreciation | B8: ='Data Sheet'!B26 -> 58.13 | C8: ='Data Sheet'!C26 -> 63.42 | D8: ='Data Sheet'!D26 -> 73.22 | E8: ='Data Sheet'!E26 -> 87.21 | F8: ='Data Sheet'!F26 -> 107.22 | G8: ='Data Sheet'!G26 -> 118.28 | H8: ='Data Sheet'!H26 -> 132.06 | I8: ='Data Sheet'!I26 -> 150.06 | ... K8: ='Data Sheet'!K26 -> 243.65 | L8: =SUM(Quarters!H8:K8) -> 246.2 | M8: =+$L8 -> 246.2 | N8: =+$L8 -> 246.2
A9: Interest | B9: ='Data Sheet'!B27 -> 51.06 | C9: ='Data Sheet'!C27 -> 32.21 | D9: ='Data Sheet'!D27 -> 29.49 | E9: ='Data Sheet'!E27 -> 19.54 | F9: ='Data Sheet'!F27 -> 17.23 | G9: ='Data Sheet'!G27 -> 13.34 | H9: ='Data Sheet'!H27 -> 14.97 | I9: ='Data Sheet'!I27 -> 13.27 | ... K9: ='Data Sheet'!K27 -> 29.17 | L9: =SUM(Quarters!H9:K9) -> 29.2 | M9: =+$L9 -> 29.2 | N9: =+$L9 -> 29.2
A10: Profit before tax | B10: ='Data Sheet'!B28 -> 82.42 | C10: ='Data Sheet'!C28 -> 208 | D10: ='Data Sheet'!D28 -> 509.08 | E10: ='Data Sheet'!E28 -> 715.01 | F10: ='Data Sheet'!F28 -> 625.25 | G10: ='Data Sheet'!G28 -> 1154.78 | H10: ='Data Sheet'!H28 -> 992.83 | I10: ='Data Sheet'!I28 -> 834.59 | ... K10: ='Data Sheet'!K28 -> 1491.9 | L10: =SUM(Quarters!H10:K10) -> 1504.64 | M10: =M6+M7-SUM(M8:M9) -> 1056.104 | N10: =N6+N7-SUM(N8:N9) -> 877.73933
A11: Tax | B11: ='Data Sheet'!B29 -> 12.27 | C11: ='Data Sheet'!C29 -> 77.25 | D11: ='Data Sheet'!D29 -> 162.49 | E11: ='Data Sheet'!E29 -> 237.11 | F11: ='Data Sheet'!F29 -> 153.53 | G11: ='Data Sheet'!G29 -> 283.15 | H11: ='Data Sheet'!H29 -> 257.22 | I11: ='Data Sheet'!I29 -> 197.94 | ... K11: ='Data Sheet'!K29 -> 226.95 | L11: =SUM(Quarters!H11:K11) -> 239.69 | M11: =IF($L10>0,$L11/$L10,0) -> 0.15930056 | N11: =IF($L10>0,$L11/$L10,0) -> 0.15930056
A12: Net profit | B12: ='Data Sheet'!B30 -> 70.61 | C12: ='Data Sheet'!C30 -> 131.27 | D12: ='Data Sheet'!D30 -> 347.02 | E12: ='Data Sheet'!E30 -> 478.93 | F12: ='Data Sheet'!F30 -> 472.25 | G12: ='Data Sheet'!G30 -> 871.46 | H12: ='Data Sheet'!H30 -> 736.47 | I12: ='Data Sheet'!I30 -> 636.78 | ... K12: ='Data Sheet'!K30 -> 1264.94 | L12: =SUM(Quarters!H12:K12) -> 1264.94 | M12: =M10-M11*M10 -> 887.86605 | N12: =N10-N11*N10 -> 737.91496
A13: EPS | B13: =IF('Data Sheet'!B93>0,B12/'Data Sheet'!B93,0) -> 5.7593801 | C13: =IF('Data Sheet'!C93>0,C12/'Data Sheet'!C93,0) -> 10.707178 | D13: =IF('Data Sheet'!D93>0,D12/'Data Sheet'!D93,0) -> 28.305057 | E13: =IF('Data Sheet'!E93>0,E12/'Data Sheet'!E93,0) -> 39.064437 | F13: =IF('Data Sheet'!F93>0,F12/'Data Sheet'!F93,0) -> 38.519576 | G13: =IF('Data Sheet'!G93>0,G12/'Data Sheet'!G93,0) -> 64.648368 | H13: =IF('Data Sheet'!H93>0,H12/'Data Sheet'!H93,0) -> 55.835481 | I13: =IF('Data Sheet'!I93>0,I12/'Data Sheet'!I93,0) -> 48.277483 | ... K13: =IF('Data Sheet'!K93>0,K12/'Data Sheet'!K93,0) -> 113.042 | L13: =IF('Data Sheet'!$B6>0,'Profit & Loss'!L12/'Data Sheet'!$B6,0) -> 113.06443 | M13: =IF('Data Sheet'!$B6>0,'Profit & Loss'!M12/'Data Sheet'!$B6,0) -> 79.360344 | N13: =IF('Data Sheet'!$B6>0,'Profit & Loss'!N12/'Data Sheet'!$B6,0) -> 65.95723
A14: Price to earning | B14: =IF(B15>0,B15/B13,"") -> 24.177949 | C14: =IF(C15>0,C15/C13,"") -> 50.316714 | D14: =IF(D15>0,D15/D13,"") -> 28.902962 | E14: =IF(E15>0,E15/E13,"") -> 20.377869 | F14: =IF(F15>0,F15/F13,"") -> 17.201643 | G14: =IF(G15>0,G15/G13,"") -> 19.92007 | H14: =IF(H15>0,H15/H13,"") -> 30.282716 | I14: =IF(I15>0,I15/I13,"") -> 39.170435 | ... K14: =IF(K15>0,K15/K13,"") -> 28.750818 | L14: =IF(L13>0,L15/L13,0) -> 29.239964 | M14: =M25 -> 31.416382 | N14: =N25 -> 26.680978
A15: Price | B15: ='Data Sheet'!B90 -> 139.25 | C15: ='Data Sheet'!C90 -> 538.75 | D15: ='Data Sheet'!D90 -> 818.1 | E15: ='Data Sheet'!E90 -> 796.05 | F15: ='Data Sheet'!F90 -> 662.6 | G15: ='Data Sheet'!G90 -> 1287.8 | H15: ='Data Sheet'!H90 -> 1690.85 | I15: ='Data Sheet'!I90 -> 1891.05 | ... K15: ='Data Sheet'!K90 -> 3250.05 | L15: ='Data Sheet'!B8 -> 3306 | M15: =M13*M14 -> 2493.2148 | N15: =N13*N14 -> 1759.8034
A17: RATIOS:
A18: Dividend Payout | B18: =IF('Data Sheet'!B30>0, 'Data Sheet'!B31/'Data Sheet'!B30, 0) -> 0.20832743 | C18: =IF('Data Sheet'!C30>0, 'Data Sheet'!C31/'Data Sheet'!C30, 0) -> 0.14009294 | D18: =IF('Data Sheet'!D30>0, 'Data Sheet'!D31/'Data Sheet'!D30, 0) -> 0.070658752 | E18: =IF('Data Sheet'!E30>0, 'Data Sheet'!E31/'Data Sheet'!E30, 0) -> 0.063975946 | F18: =IF('Data Sheet'!F30>0, 'Data Sheet'!F31/'Data Sheet'!F30, 0) -> 0.064880889 | G18: =IF('Data Sheet'!G30>0, 'Data Sheet'!G31/'Data Sheet'!G30, 0) -> 0.11603516 | H18: =IF('Data Sheet'!H30>0, 'Data Sheet'!H31/'Data Sheet'!H30, 0) -> 0.12540905 | I18: =IF('Data Sheet'!I30>0, 'Data Sheet'!I31/'Data Sheet'!I30, 0) -> 0.14504224 | ... K18: =IF('Data Sheet'!K30>0, 'Data Sheet'!K31/'Data Sheet'!K30, 0) -> 0.24764811
A19: OPM | B19: =IF(B6>0,B6/B4,0) -> 0.04689699 | C19: =IF(C6>0,C6/C4,0) -> 0.064597993 | D19: =IF(D6>0,D6/D4,0) -> 0.10937197 | E19: =IF(E6>0,E6/E4,0) -> 0.11538928 | F19: =IF(F6>0,F6/F4,0) -> 0.11382268 | G19: =IF(G6>0,G6/G4,0) -> 0.16052931 | H19: =IF(H6>0,H6/H4,0) -> 0.13265226 | I19: =IF(I6>0,I6/I4,0) -> 0.091359393 | ... L19: =IF(L6>0,L6/L4,0) -> 0.11600757
G22: TRENDS: | H22: 10 YEARS | I22: 7 YEARS | J22: 5 YEARS | K22: 3 YEARS | L22: RECENT | M22: BEST | N22: WORST
G23: Sales Growth | H23: =IF(B4=0,"",POWER($K4/B4,1/9)-1) -> 0.12919441 | I23: =IF(D4=0,"",POWER($K4/D4,1/7)-1) -> 0.10603083 | J23: =IF(F4=0,"",POWER($K4/F4,1/5)-1) -> 0.12009878 | K23: =IF(H4=0,"",POWER($K4/H4, 1/3)-1) -> 0.12044794 | L23: =IF(ISERROR(MAX(IF(J4=0,"",(K4-J4)/J4),IF(K4=0,"",(L4-K4)/K4))),"",MAX(IF(J4=0,"",(K4-J4)/J4),IF(K4=0,"",(L4-K4)/K4))) -> 0.044911099 | M23: =MAX(K23:L23) -> 0.12044794 | N23: =MIN(H23:L23) -> 0.044911099
G24: OPM | H24: =IF(SUM(B4:$K$4)=0,"",SUMPRODUCT(B19:$K$19,B4:$K$4)/SUM(B4:$K$4)) -> 0.11147639 | I24: =IF(SUM(E4:$K$4)=0,"",SUMPRODUCT(E19:$K$19,E4:$K$4)/SUM(E4:$K$4)) -> 0.1192548 | J24: =IF(SUM(G4:$K$4)=0,"",SUMPRODUCT(G19:$K$19,G4:$K$4)/SUM(G4:$K$4)) -> 0.12055858 | K24: =IF(SUM(I4:$K$4)=0, "", SUMPRODUCT(I19:$K$19,I4:$K$4)/SUM(I4:$K$4)) -> 0.10761985 | L24: =L19 -> 0.11600757 | M24: =MAX(K24:L24) -> 0.11600757 | N24: =MIN(H24:L24) -> 0.10761985
G25: Price to Earning | H25: =IF(ISERROR(AVERAGEIF(B14:$L14,">0")),"",AVERAGEIF(B14:$L14,">0")) -> 28.804132 | I25: =IF(ISERROR(AVERAGEIF(E14:$L14,">0")),"",AVERAGEIF(E14:$L14,">0")) -> 26.680978 | J25: =IF(ISERROR(AVERAGEIF(G14:$L14,">0")),"",AVERAGEIF(G14:$L14,">0")) -> 29.311385 | K25: =IF(ISERROR(AVERAGEIF(I14:$L14,">0")),"",AVERAGEIF(I14:$L14,">0")) -> 31.416382 | L25: =L14 -> 29.239964 | M25: =MAX(K25:L25) -> 31.416382 | N25: =MIN(H25:L25) -> 26.680978

Sheet Quarters
A1: ='Profit & Loss'!A1 -> ESCORTS KUBOTA LTD | E1: =UPDATE | J1: SCREENER.IN
A3: Narration | B3: ='Data Sheet'!B41 -> 44926 | C3: ='Data Sheet'!C41 -> 45016 | D3: ='Data Sheet'!D41 -> 45107 | E3: ='Data Sheet'!E41 -> 45199 | F3: ='Data Sheet'!F41 -> 45291 | G3: ='Data Sheet'!G41 -> 45382 | H3: ='Data Sheet'!H41 -> 45473 | I3: ='Data Sheet'!I41 -> 45565 | ... K3: ='Data Sheet'!K41 -> 45747
A4: Sales | B4: ='Data Sheet'!B42 -> 2291.35 | C4: ='Data Sheet'!C42 -> 2214.48 | D4: ='Data Sheet'!D42 -> 2355.17 | E4: ='Data Sheet'!E42 -> 2477.71 | F4: ='Data Sheet'!F42 -> 2727.61 | G4: ='Data Sheet'!G42 -> 2300.66 | H4: ='Data Sheet'!H42 -> 2818.39 | I4: ='Data Sheet'!I42 -> 2277.25 | ... K4: ='Data Sheet'!K42 -> 2444.88
A5: Expenses | B5: ='Data Sheet'!B43 -> 2105.96 | C5: ='Data Sheet'!C43 -> 1981.32 | D5: ='Data Sheet'!D43 -> 2024.12 | E5: ='Data Sheet'!E43 -> 2213.52 | F5: ='Data Sheet'!F43 -> 2402.32 | G5: ='Data Sheet'!G43 -> 2015.25 | H5: ='Data Sheet'!H43 -> 2450.99 | I5: ='Data Sheet'!I43 -> 2047.43 | ... K5: ='Data Sheet'!K43 -> 2157.63
A6: Operating Profit | B6: ='Data Sheet'!B50 -> 185.39 | C6: ='Data Sheet'!C50 -> 233.16 | D6: ='Data Sheet'!D50 -> 331.05 | E6: ='Data Sheet'!E50 -> 264.19 | F6: ='Data Sheet'!F50 -> 325.29 | G6: ='Data Sheet'!G50 -> 285.41 | H6: ='Data Sheet'!H50 -> 367.4 | I6: ='Data Sheet'!I50 -> 229.82 | ... K6: ='Data Sheet'!K50 -> 287.25
A7: Other Income | B7: ='Data Sheet'!B44 -> 91.68 | C7: ='Data Sheet'!C44 -> 86.46 | D7: ='Data Sheet'!D44 -> 99.02 | E7: ='Data Sheet'!E44 -> 93.75 | F7: ='Data Sheet'!F44 -> 128.6 | G7: ='Data Sheet'!G44 -> 132.77 | H7: ='Data Sheet'!H44 -> 103.04 | I7: ='Data Sheet'!I44 -> 140.05 | ... K7: ='Data Sheet'!K44 -> 177.6
A8: Depreciation | B8: ='Data Sheet'!B45 -> 37.97 | C8: ='Data Sheet'!C45 -> 38.37 | D8: ='Data Sheet'!D45 -> 40.3 | E8: ='Data Sheet'!E45 -> 58.34 | F8: ='Data Sheet'!F45 -> 56.62 | G8: ='Data Sheet'!G45 -> 59.24 | H8: ='Data Sheet'!H45 -> 61.63 | I8: ='Data Sheet'!I45 -> 61.07 | ... K8: ='Data Sheet'!K45 -> 61.97
A9: Interest | B9: ='Data Sheet'!B46 -> 3.48 | C9: ='Data Sheet'!C46 -> 3.63 | D9: ='Data Sheet'!D46 -> 3.43 | E9: ='Data Sheet'!E46 -> 9.43 | F9: ='Data Sheet'!F46 -> 11.16 | G9: ='Data Sheet'!G46 -> 11.66 | H9: ='Data Sheet'!H46 -> 10.73 | I9: ='Data Sheet'!I46 -> 9.79 | ... K9: ='Data Sheet'!K46 -> 5.14
A10: Profit before tax | B10: ='Data Sheet'!B47 -> 235.62 | C10: ='Data Sheet'!C47 -> 277.62 | D10: ='Data Sheet'!D47 -> 386.34 | E10: ='Data Sheet'!E47 -> 290.17 | F10: ='Data Sheet'!F47 -> 386.11 | G10: ='Data Sheet'!G47 -> 347.28 | H10: ='Data Sheet'!H47 -> 398.08 | I10: ='Data Sheet'!I47 -> 299.01 | ... K10: ='Data Sheet'!K47 -> 397.74
A11: Tax | B11: ='Data Sheet'!B48 -> 54.82 | C11: ='Data Sheet'!C48 -> 61.16 | D11: ='Data Sheet'!D48 -> 96.45 | E11: ='Data Sheet'!E48 -> 79.66 | F11: ='Data Sheet'!F48 -> 87.59 | G11: ='Data Sheet'!G48 -> 77.3 | H11: ='Data Sheet'!H48 -> 96.4 | I11: ='Data Sheet'!I48 -> -25.21 | ... K11: ='Data Sheet'!K48 -> 79.32
A12: Net profit | B12: ='Data Sheet'!B49 -> 180.82 | C12: ='Data Sheet'!C49 -> 216.49 | D12: ='Data Sheet'!D49 -> 289.9 | E12: ='Data Sheet'!E49 -> 210.53 | F12: ='Data Sheet'!F49 -> 298.51 | G12: ='Data Sheet'!G49 -> 269.99 | H12: ='Data Sheet'!H49 -> 301.65 | I12: ='Data Sheet'!I49 -> 324.23 | ... K12: ='Data Sheet'!K49 -> 318.42
A14: OPM | B14: =IF(B4>0,B6/B4,"") -> 0.080908635 | C14: =IF(C4>0,C6/C4,"") -> 0.10528883 | D14: =IF(D4>0,D6/D4,"") -> 0.1405631 | E14: =IF(E4>0,E6/E4,"") -> 0.10662668 | F14: =IF(F4>0,F6/F4,"") -> 0.11925825 | G14: =IF(G4>0,G6/G4,"") -> 0.12405571 | H14: =IF(H4>0,H6/H4,"") -> 0.13035811 | I14: =IF(I4>0,I6/I4,"") -> 0.10091997 | ... K14: =IF(K4>0,K6/K4,"") -> 0.11749043

Sheet Balance Sheet
A1: ='Profit & Loss'!A1 -> ESCORTS KUBOTA LTD | E1: =UPDATE | J1: SCREENER.IN
A3: Narration | B3: ='Data Sheet'!B56 -> 42460 | C3: ='Data Sheet'!C56 -> 42825 | D3: ='Data Sheet'!D56 -> 43190 | E3: ='Data Sheet'!E56 -> 43555 | F3: ='Data Sheet'!F56 -> 43921 | G3: ='Data Sheet'!G56 -> 44286 | H3: ='Data Sheet'!H56 -> 44651 | I3: ='Data Sheet'!I56 -> 45016 | ... K3: ='Data Sheet'!K56 -> 45747
A4: Equity Share Capital | B4: ='Data Sheet'!B57 -> 122.58 | C4: ='Data Sheet'!C57 -> 122.58 | D4: ='Data Sheet'!D57 -> 122.58 | E4: ='Data Sheet'!E57 -> 122.58 | F4: ='Data Sheet'!F57 -> 122.58 | G4: ='Data Sheet'!G57 -> 134.83 | H4: ='Data Sheet'!H57 -> 131.94 | I4: ='Data Sheet'!I57 -> 131.94 | ... K4: ='Data Sheet'!K57 -> 111.88
A5: Reserves | B5: ='Data Sheet'!B58 -> 1343.9 | C5: ='Data Sheet'!C58 -> 1498.35 | D5: ='Data Sheet'!D58 -> 2092.56 | E5: ='Data Sheet'!E58 -> 2550.91 | F5: ='Data Sheet'!F58 -> 2994.82 | G5: ='Data Sheet'!G58 -> 4891.3 | H5: ='Data Sheet'!H58 -> 7467.96 | I5: ='Data Sheet'!I58 -> 8054.77 | ... K5: ='Data Sheet'!K58 -> 10254.92
A6: Borrowings | B6: ='Data Sheet'!B59 -> 368.12 | C6: ='Data Sheet'!C59 -> 265.43 | D6: ='Data Sheet'!D59 -> 51.09 | E6: ='Data Sheet'!E59 -> 280.96 | F6: ='Data Sheet'!F59 -> 47.67 | G6: ='Data Sheet'!G59 -> 60.61 | H6: ='Data Sheet'!H59 -> 51.95 | I6: ='Data Sheet'!I59 -> 57.3 | ... K6: ='Data Sheet'!K59 -> 105.18
A7: Other Liabilities | B7: ='Data Sheet'!B60 -> 1133.58 | C7: ='Data Sheet'!C60 -> 1312.86 | D7: ='Data Sheet'!D60 -> 1706.3 | E7: ='Data Sheet'!E60 -> 1752.52 | F7: ='Data Sheet'!F60 -> 1848.89 | G7: ='Data Sheet'!G60 -> 1791.43 | H7: ='Data Sheet'!H60 -> 1455.89 | I7: ='Data Sheet'!I60 -> 1840.81 | ... K7: ='Data Sheet'!K60 -> 2622.71
A8: Total | B8: ='Data Sheet'!B61 -> 2968.18 | C8: ='Data Sheet'!C61 -> 3199.22 | D8: ='Data Sheet'!D61 -> 3972.53 | E8: ='Data Sheet'!E61 -> 4706.97 | F8: ='Data Sheet'!F61 -> 5013.96 | G8: ='Data Sheet'!G61 -> 6878.17 | H8: ='Data Sheet'!H61 -> 9107.74 | I8: ='Data Sheet'!I61 -> 10084.82 | ... K8: ='Data Sheet'!K61 -> 13094.69
A10: Net Block | B10: ='Data Sheet'!B62 -> 1539.02 | C10: ='Data Sheet'!C62 -> 1581.14 | D10: ='Data Sheet'!D62 -> 1587.8 | E10: ='Data Sheet'!E62 -> 1647.23 | F10: ='Data Sheet'!F62 -> 1702.41 | G10: ='Data Sheet'!G62 -> 1796.23 | H10: ='Data Sheet'!H62 -> 1841.05 | I10: ='Data Sheet'!I62 -> 1891.15 | ... K10: ='Data Sheet'!K62 -> 2053.18
A11: Capital Work in Progress | B11: ='Data Sheet'!B63 -> 58.43 | C11: ='Data Sheet'!C63 -> 34.7 | D11: ='Data Sheet'!D63 -> 65.72 | E11: ='Data Sheet'!E63 -> 79.96 | F11: ='Data Sheet'!F63 -> 124.66 | G11: ='Data Sheet'!G63 -> 64.69 | H11: ='Data Sheet'!H63 -> 87.8 | I11: ='Data Sheet'!I63 -> 113.68 | ... K11: ='Data Sheet'!K63 -> 152.54
A12: Investments | B12: ='Data Sheet'!B64 -> 63.66 | C12: ='Data Sheet'!C64 -> 212.34 | D12: ='Data Sheet'!D64 -> 549.04 | E12: ='Data Sheet'!E64 -> 490.79 | F12: ='Data Sheet'!F64 -> 797.36 | G12: ='Data Sheet'!G64 -> 1938.02 | H12: ='Data Sheet'!H64 -> 4835.84 | I12: ='Data Sheet'!I64 -> 4766.69 | ... K12: ='Data Sheet'!K64 -> 5605.21
A13: Other Assets | B13: ='Data Sheet'!B65 -> 1307.07 | C13: ='Data Sheet'!C65 -> 1371.04 | D13: ='Data Sheet'!D65 -> 1769.97 | E13: ='Data Sheet'!E65 -> 2488.99 | F13: ='Data Sheet'!F65 -> 2389.53 | G13: ='Data Sheet'!G65 -> 3079.23 | H13: ='Data Sheet'!H65 -> 2343.05 | I13: ='Data Sheet'!I65 -> 3313.3 | ... K13: ='Data Sheet'!K65 -> 5283.76
A14: Total | B14: ='Data Sheet'!B66 -> 2968.18 | C14: ='Data Sheet'!C66 -> 3199.22 | D14: ='Data Sheet'!D66 -> 3972.53 | E14: ='Data Sheet'!E66 -> 4706.97 | F14: ='Data Sheet'!F66 -> 5013.96 | G14: ='Data Sheet'!G66 -> 6878.17 | H14: ='Data Sheet'!H66 -> 9107.74 | I14: ='Data Sheet'!I66 -> 10084.82 | ... K14: ='Data Sheet'!K66 -> 13094.69
A16: Working Capital | B16: =B13-B7 -> 173.49 | C16: =C13-C7 -> 58.18 | D16: =D13-D7 -> 63.67 | E16: =E13-E7 -> 736.47 | F16: =F13-F7 -> 540.64 | G16: =G13-G7 -> 1287.8 | H16: =H13-H7 -> 887.16 | I16: =I13-I7 -> 1472.49 | ... K16: =K13-K7 -> 2661.05
A17: Debtors | B17: ='Data Sheet'!B67 -> 374.97 | C17: ='Data Sheet'!C67 -> 456.45 | D17: ='Data Sheet'!D67 -> 592 | E17: ='Data Sheet'!E67 -> 931.05 | F17: ='Data Sheet'!F67 -> 731.86 | G17: ='Data Sheet'!G67 -> 657.58 | H17: ='Data Sheet'!H67 -> 792.62 | I17: ='Data Sheet'!I67 -> 1179.65 | ... K17: ='Data Sheet'!K67 -> 1331.84
A18: Inventory | B18: ='Data Sheet'!B68 -> 456.76 | C18: ='Data Sheet'!C68 -> 450.3 | D18: ='Data Sheet'!D68 -> 565.73 | E18: ='Data Sheet'!E68 -> 857.42 | F18: ='Data Sheet'!F68 -> 883.36 | G18: ='Data Sheet'!G68 -> 718.16 | H18: ='Data Sheet'!H68 -> 846.56 | I18: ='Data Sheet'!I68 -> 1217.68 | ... K18: ='Data Sheet'!K68 -> 1398.99
A20: Debtor Days | B20: =IF('Profit & Loss'!B4>0,'Balance Sheet'!B17/('Profit & Loss'!B4/365),0) -> 39.878919 | C20: =IF('Profit & Loss'!C4>0,'Balance Sheet'!C17/('Profit & Loss'!C4/365),0) -> 40.190829 | D20: =IF('Profit & Loss'!D4>0,'Balance Sheet'!D17/('Profit & Loss'!D4/365),0) -> 42.709128 | E20: =IF('Profit & Loss'!E4>0,'Balance Sheet'!E17/('Profit & Loss'!E4/365),0) -> 54.26895 | F20: =IF('Profit & Loss'!F4>0,'Balance Sheet'!F17/('Profit & Loss'!F4/365),0) -> 45.976723 | G20: =IF('Profit & Loss'!G4>0,'Balance Sheet'!G17/('Profit & Loss'!G4/365),0) -> 34.217612 | H20: =IF('Profit & Loss'!H4>0,'Balance Sheet'!H17/('Profit & Loss'!H4/365),0) -> 39.725416 | I20: =IF('Profit & Loss'!I4>0,'Balance Sheet'!I17/('Profit & Loss'!I4/365),0) -> 51.084125 | ... K20: =IF('Profit & Loss'!K4>0,'Balance Sheet'!K17/('Profit & Loss'!K4/365),0) -> 47.454832
A21: Inventory Turnover | B21: =IF('Balance Sheet'!B18>0,'Profit & Loss'!B4/'Balance Sheet'!B18,0) -> 7.5137709 | C21: =IF('Balance Sheet'!C18>0,'Profit & Loss'!C4/'Balance Sheet'!C18,0) -> 9.2057073 | D21: =IF('Balance Sheet'!D18>0,'Profit & Loss'!D4/'Balance Sheet'!D18,0) -> 8.9430294 | E21: =IF('Balance Sheet'!E18>0,'Profit & Loss'!E4/'Balance Sheet'!E18,0) -> 7.3033286 | F21: =IF('Balance Sheet'!F18>0,'Profit & Loss'!F4/'Balance Sheet'!F18,0) -> 6.5772618 | G21: =IF('Balance Sheet'!G18>0,'Profit & Loss'!G4/'Balance Sheet'!G18,0) -> 9.7672106 | H21: =IF('Balance Sheet'!H18>0,'Profit & Loss'!H4/'Balance Sheet'!H18,0) -> 8.6026389 | I21: =IF('Balance Sheet'!I18>0,'Profit & Loss'!I4/'Balance Sheet'!I18,0) -> 6.9219253 | ... K21: =IF('Balance Sheet'!K18>0,'Profit & Loss'!K4/'Balance Sheet'!K18,0) -> 7.3223397
A23: Return on Equity | B23: =IF(SUM('Balance Sheet'!B4:B5)>0,'Profit & Loss'!B12/SUM('Balance Sheet'!B4:B5),"") -> 0.04814931 | C23: =IF(SUM('Balance Sheet'!C4:C5)>0,'Profit & Loss'!C12/SUM('Balance Sheet'!C4:C5),"") -> 0.080984373 | D23: =IF(SUM('Balance Sheet'!D4:D5)>0,'Profit & Loss'!D12/SUM('Balance Sheet'!D4:D5),"") -> 0.15665827 | E23: =IF(SUM('Balance Sheet'!E4:E5)>0,'Profit & Loss'!E12/SUM('Balance Sheet'!E4:E5),"") -> 0.17914037 | F23: =IF(SUM('Balance Sheet'!F4:F5)>0,'Profit & Loss'!F12/SUM('Balance Sheet'!F4:F5),"") -> 0.15148842 | G23: =IF(SUM('Balance Sheet'!G4:G5)>0,'Profit & Loss'!G12/SUM('Balance Sheet'!G4:G5),"") -> 0.17338589 | H23: =IF(SUM('Balance Sheet'!H4:H5)>0,'Profit & Loss'!H12/SUM('Balance Sheet'!H4:H5),"") -> 0.096905222 | I23: =IF(SUM('Balance Sheet'!I4:I5)>0,'Profit & Loss'!I12/SUM('Balance Sheet'!I4:I5),"") -> 0.077782162 | ... K23: =IF(SUM('Balance Sheet'!K4:K5)>0,'Profit & Loss'!K12/SUM('Balance Sheet'!K4:K5),"") -> 0.12201837
A24: Return on Capital Emp | C24: =IF((B4+B5+B6+C4+C5+C6)>0,('Profit & Loss'!C10+'Profit & Loss'!C9)*2/(B4+B5+B6+C4+C5+C6),"") -> 0.12911184 | D24: =IF((C4+C5+C6+D4+D5+D6)>0,('Profit & Loss'!D10+'Profit & Loss'!D9)*2/(C4+C5+C6+D4+D5+D6),"") -> 0.25938992 | E24: =IF((D4+D5+D6+E4+E5+E6)>0,('Profit & Loss'!E10+'Profit & Loss'!E9)*2/(D4+D5+D6+E4+E5+E6),"") -> 0.28140012 | F24: =IF((E4+E5+E6+F4+F5+F6)>0,('Profit & Loss'!F10+'Profit & Loss'!F9)*2/(E4+E5+E6+F4+F5+F6),"") -> 0.20997725 | G24: =IF((F4+F5+F6+G4+G5+G6)>0,('Profit & Loss'!G10+'Profit & Loss'!G9)*2/(F4+F5+F6+G4+G5+G6),"") -> 0.28311849 | H24: =IF((G4+G5+G6+H4+H5+H6)>0,('Profit & Loss'!H10+'Profit & Loss'!H9)*2/(G4+G5+G6+H4+H5+H6),"") -> 0.15822787 | I24: =IF((H4+H5+H6+I4+I5+I6)>0,('Profit & Loss'!I10+'Profit & Loss'!I9)*2/(H4+H5+H6+I4+I5+I6),"") -> 0.10667683 | J24: =IF((I4+I5+I6+J4+J5+J6)>0,('Profit & Loss'!J10+'Profit & Loss'!J9)*2/(I4+I5+I6+J4+J5+J6),"") -> 0.1583631 | K24: =IF((J4+J5+J6+K4+K5+K6)>0,('Profit & Loss'!K10+'Profit & Loss'!K9)*2/(J4+J5+J6+K4+K5+K6),"") -> 0.14979307

Sheet Cash Flow
A1: ='Balance Sheet'!A1 -> ESCORTS KUBOTA LTD | E1: =UPDATE | J1: SCREENER.IN
A3: Narration | B3: ='Data Sheet'!B81 -> 42460 | C3: ='Data Sheet'!C81 -> 42825 | D3: ='Data Sheet'!D81 -> 43190 | E3: ='Data Sheet'!E81 -> 43555 | F3: ='Data Sheet'!F81 -> 43921 | G3: ='Data Sheet'!G81 -> 44286 | H3: ='Data Sheet'!H81 -> 44651 | I3: ='Data Sheet'!I81 -> 45016 | ... K3: ='Data Sheet'!K81 -> 45747
A4: Cash from Operating Activity | B4: ='Data Sheet'!B82 -> 212.24 | C4: ='Data Sheet'!C82 -> 303.83 | D4: ='Data Sheet'!D82 -> 460.08 | E4: ='Data Sheet'!E82 -> -234.31 | F4: ='Data Sheet'!F82 -> 797.16 | G4: ='Data Sheet'!G82 -> 1128.66 | H4: ='Data Sheet'!H82 -> 32.28 | I4: ='Data Sheet'!I82 -> 223.91 | ... K4: ='Data Sheet'!K82 -> 1003.19
A5: Cash from Investing Activity | B5: ='Data Sheet'!B83 -> -44.09 | C5: ='Data Sheet'!C83 -> -154.61 | D5: ='Data Sheet'!D83 -> -374.18 | E5: ='Data Sheet'!E83 -> -17.66 | F5: ='Data Sheet'!F83 -> -420.87 | G5: ='Data Sheet'!G83 -> -2195.15 | H5: ='Data Sheet'!H83 -> -1856.39 | I5: ='Data Sheet'!I83 -> -62.05 | ... K5: ='Data Sheet'!K83 -> -193.85
A6: Cash from Financing Activity | B6: ='Data Sheet'!B84 -> -190.89 | C6: ='Data Sheet'!C84 -> -113.12 | D6: ='Data Sheet'!D84 -> -0.99 | E6: ='Data Sheet'!E84 -> 190.89 | F6: ='Data Sheet'!F84 -> -300.45 | G6: ='Data Sheet'!G84 -> 1003.34 | H6: ='Data Sheet'!H84 -> 1809.88 | I6: ='Data Sheet'!I84 -> -71.22 | ... K6: ='Data Sheet'!K84 -> -701.86
A7: Net Cash Flow | B7: ='Data Sheet'!B85 -> -22.74 | C7: ='Data Sheet'!C85 -> 36.1 | D7: ='Data Sheet'!D85 -> 84.91 | E7: ='Data Sheet'!E85 -> -61.08 | F7: ='Data Sheet'!F85 -> 75.84 | G7: ='Data Sheet'!G85 -> -63.15 | H7: ='Data Sheet'!H85 -> -14.23 | I7: ='Data Sheet'!I85 -> 90.64 | ... K7: ='Data Sheet'!K85 -> 107.48

Sheet Customization
A1: How to use it?
A3: You can customize this workbook as you want.
B4: You can add custom formating, add conditional formating, add your own formulas… do ANYTHING.
B5: Please don't edit the "Data Sheet" only.
A7: After customization, you can upload this back on Screener.
B8: Upload on: | C8: https://www.screener.in/excel/
A10: Download your customized workbooks now onwards.
B11: Now whenever you will "Export to excel" from Screener, it will export your customized file.
A14: TESTING:
B15: This is a testing feature currently.
B16: You can report any formula errors on the worksheet at: support@screener.in
